[
  {
    "query": "zimní dovolená",
    "language": "queries",
    "results": [
      {
        "title": "Cestovní kancelář Nev-Dama - Zimní dovolená",
        "href": "https://www.nev-dama.cz/zima",
        "real_result": true
      },
      {
        "title": "Zimní dovolená s dětmi v - Penzionu Uko s bazénem zdarma.",
        "href": "https://www.uko.cz/",
        "real_result": true
      },
      {
        "title": "Dovolená 2024 - Last Minute slevy až 50 %",
        "href": "https://dovolena.cz/last-minute",
        "real_result": true
      },
      {
        "title": "Zimní dovolená s Čedokem - Zájezdy do všech koutů světa",
        "href": "https://www.cedok.cz/vysledky-vyhledavani/",
        "real_result": true
      },
      {
        "title": "Zimní pobyty | Spa.cz",
        "href": "https://www.spa.cz/program/zimni-pobyty/",
        "real_result": true
      },
      {
        "title": "Zimní pobyty | Hotel.cz",
        "href": "https://www.hotel.cz/packages/zimni-pobyty/",
        "real_result": true
      },
      {
        "title": "Sdovolená.cz›Tipy na   dovolenou  ",
        "href": "https://sdovolena.seznam.cz/search?date_from=01.12.2023&date_to=01.04.2024&sub_type=304#source:hint-advert&utm_content=sdovolena&utm_term=zimn%C3%AD%20dovolen%C3%A1&utm_medium=hint&utm_source=search.seznam.cz",
        "real_result": false
      },
      {
        "title": "Zimní dovolená | Travelking",
        "href": "https://travelking.cz/zima?page=1",
        "real_result": true
      },
      {
        "title": "Zimní dovolená na horách v ČR",
        "href": "https://www.ceskapohoda.cz/index.php/ubytovani/zimni-dovolena-na-horach",
        "real_result": true
      },
      {
        "title": "Zimní dovolená | Cestuj s dětmi.cz",
        "href": "https://www.cestujsdetmi.cz/rady-a-tipy/cestujsdetmi_doporucuje/zimni-dovolena",
        "real_result": true
      },
      {
        "title": "Zima | CK České kormidlo",
        "href": "https://ceskekormidlo.cz/zima/",
        "real_result": true
      },
      {
        "title": "Zimní dovolená 2024 jakou si přejete - dovolena.cz",
        "href": "https://dovolena.cz/zima-na-horach",
        "real_result": true
      },
      {
        "title": "Dovolená na horách - Skrz.cz",
        "href": "https://skrz.cz/dovolena-hory",
        "real_result": true
      },
      {
        "title": "Zimní dovolená a ubytování na horách v chatě nebo chalupě 2024",
        "href": "https://www.alkatravel.cz/cs/dovolena-zima",
        "real_result": true
      },
      {
        "title": "Zimní dovolená 2023/2024 u moře i na horách | Zájezdy.cz",
        "href": "https://www.zajezdy.cz/dovolena-zima/",
        "real_result": true
      },
      {
        "title": "Levná dovolená 2024 - First minute dovolená",
        "href": "https://skrz.cz/dovolena-more",
        "real_result": true
      },
      {
        "title": "Zimni dovolena - newtravel.cz",
        "href": "http://www.newtravel.cz/",
        "real_result": true
      },
      {
        "title": "Nabídky ze Zboží.cz",
        "href": "https://www.zbozi.cz/nabidka/9b5002002a8a812400df8963b2e2ac0ed01b07b8/",
        "real_result": false
      }
    ],
    "user": "anon_dp_tool",
    "timestamp": "2024-03-26T07:33:00.513Z"
  },
  {
    "query": "mapy na turistiku",
    "language": "queries",
    "results": [
      {
        "title": "Turistické mapy - Největší online tržiště",
        "href": "https://aukro.cz/turisticke-mapy",
        "real_result": true
      },
      {
        "title": "Turistické mapy na Alza.cz - Možnost vrácení do 60 dnů",
        "href": "https://www.alza.cz/media/turisticke-mapy/18886362.htm",
        "real_result": true
      },
      {
        "title": "Obrázky›Mapy na turistiku",
        "href": "/obrazky/?q=mapy+na+turistiku&fulltext=&sourceid=fulltext&thru=hint-obrazky-super#utm_content=super&utm_term=mapy%20na%20turistiku&utm_medium=hint&utm_source=search.seznam.cz",
        "real_result": false
      },
      {
        "title": "Turistická mapa – Wikipedie",
        "href": "https://cs.wikipedia.org/wiki/Turistick%C3%A1_mapa#:~:text=Turistick%C3%A1%20mapa%20je%20druh%20kartografick%C3%A9,(tedy%201%20cm%20na%20map%C4%9B",
        "real_result": true
      },
      {
        "title": "Mapy.cz – nejlepší turistické offline mapy do mobilu zdarma",
        "href": "https://www.autovylet.cz/mapy-cz-nejlepsi-turisticke-offline-mapy-do-mobilu-zdarma/",
        "real_result": true
      },
      {
        "title": "Zboží.cz›Mapy na turistiku",
        "href": "https://www.zbozi.cz/hledej/?q=mapy%20na%20turistiku#utm_source=search.seznam.cz&utm_medium=hint&utm_content=products-opesBB&utm_ab=3120%2F5725%2C3179%2F5830%2C3178%2F5828%2C3122%2F5728%2C3121%2F5726%2C3166%2F5790&utm_term=mapy%20na%20turistiku&utm_query=mapy%20na%20turistiku",
        "real_result": false
      },
      {
        "title": "Turistické mapy | Nástěnné mapy.cz",
        "href": "https://www.nastennemapy.cz/turisticke-mapy",
        "real_result": true
      },
      {
        "title": "Turistická Mapa ČR",
        "href": "https://turistickamapa.cz/turisticke-mapy/",
        "real_result": true
      },
      {
        "title": "Turistické mapy | Turistika.cz",
        "href": "https://www.turistika.cz/mapy",
        "real_result": true
      },
      {
        "title": "Nové turistické mapy Seznamu: podrobné a s hledáním tras",
        "href": "https://www.zive.cz/clanky/nove-turisticke-mapy-seznamu-podrobne-a-s-hledanim-tras/sc-3-a-164486/default.aspx",
        "real_result": true
      },
      {
        "title": "Turistická Mapa CR - Slunečnice.cz",
        "href": "https://www.slunecnice.cz/ios/sw/turisticka-mapa-cr/",
        "real_result": true
      },
      {
        "title": "Turistické mapy – Heureka.cz",
        "href": "https://mapy-pruvodci.heureka.cz/f:15108:3066369/",
        "real_result": true
      },
      {
        "title": "Turistické, cykloturistické a speciální mapy | knihynahory.cz",
        "href": "https://www.knihynahory.cz/turisticke-mapy/",
        "real_result": true
      },
      {
        "title": "Turistické mapy | Alza.cz",
        "href": "https://www.alza.cz/media/turisticke-mapy/18886362.htm",
        "real_result": true
      },
      {
        "title": "Naučné stezky a trasy - Tipy na výlety po Česku",
        "href": "https://www.kudyznudy.cz/co-chcete-delat/priroda/naucne-stezky-a-trasy",
        "real_result": true
      },
      {
        "title": "Turistické mapy - Knihy Dobrovský",
        "href": "https://www.knihydobrovsky.cz/turisticke-pruvodce-2550",
        "real_result": true
      }
    ],
    "user": "anon_dp_tool",
    "timestamp": "2024-03-26T07:49:45.354Z"
  },
  {
    "query": "fotbal",
    "language": "queries",
    "results": [
      {
        "title": "Fotbal.CZ",
        "href": "https://www.fotbal.cz/",
        "real_result": true
      },
      {
        "title": "Fotbal – Wikipedie",
        "href": "https://cs.wikipedia.org/wiki/Fotbal",
        "real_result": true
      },
      {
        "title": "Fotbal na Sport TV: program, kde sledovat a cena Sport1 i Sport2",
        "href": "https://www.fotbalzpravy.cz/rubriky/cesko/fotbal-na-sport-tv-program-kde-sledovat-a-cena-sport1-i-sport2_1531.html",
        "real_result": true
      },
      {
        "title": "Portál:Fotbal – Wikipedie",
        "href": "https://cs.wikipedia.org/wiki/Port%C3%A1l:Fotbal",
        "real_result": true
      },
      {
        "title": "Stream.cz›Fotbal",
        "href": "https://www.stream.cz/hledani?dotaz=fotbal#utm_content=series&utm_term=fotbal&utm_medium=hint&utm_source=search.seznam.cz",
        "real_result": false
      },
      {
        "title": "Vše o fotbalu | Mastersport.CZ",
        "href": "https://www.mastersport.cz/vse-o-fotbalu-a-194.html",
        "real_result": true
      },
      {
        "title": "Kategorie:Fotbal – Wikipedie",
        "href": "https://cs.wikipedia.org/wiki/Kategorie:Fotbal",
        "real_result": true
      },
      {
        "title": "Náš fotbal | Fotbal.CZ",
        "href": "https://www.fotbal.cz/nasfotbal/",
        "real_result": true
      },
      {
        "title": "Pravidla fotbalu | Alza.cz",
        "href": "https://www.alza.cz/sport/pravidla-fotbalu",
        "real_result": true
      },
      {
        "title": "Soutěže | Fotbal.CZ",
        "href": "https://www.fotbal.cz/souteze/",
        "real_result": true
      },
      {
        "title": "Fotbal | Aktuální fotbalové výsledky, zprávy, videa, tabulky…",
        "href": "https://isport.blesk.cz/fotbal",
        "real_result": true
      }
    ],
    "user": "anon_dp_tool",
    "timestamp": "2024-03-26T08:06:23.388Z"
  },
  {
    "query": "linux",
    "language": "queries",
    "results": [
      {
        "title": "Linux.cz - České stránky systému GNU/Linux",
        "href": "http://www.linux.cz/",
        "real_result": true
      },
      {
        "title": "Linux.org",
        "href": "https://www.linux.org/",
        "real_result": true
      },
      {
        "title": "Linux – Wikipedie",
        "href": "https://cs.wikipedia.org/wiki/Linux",
        "real_result": true
      },
      {
        "title": "Co je Linux? | Peach-dev",
        "href": "https://peach-dev.cz/wiki/linux/",
        "real_result": true
      },
      {
        "title": "Zboží.cz›Linux",
        "href": "https://www.zbozi.cz/hledej/?q=linux#utm_source=search.seznam.cz&utm_medium=hint&utm_content=products-opesBB&utm_ab=3120%2F5725%2C3179%2F5830%2C3178%2F5828%2C3122%2F5728%2C3121%2F5726%2C3166%2F5790&utm_term=linux&utm_query=linux",
        "real_result": false
      },
      {
        "title": "Portál:Linux – Wikipedie",
        "href": "https://cs.wikipedia.org/wiki/Port%C3%A1l:Linux",
        "real_result": true
      },
      {
        "title": "Operační systém Linux | Datart",
        "href": "https://www.datart.cz/novinky/technologie/operacni-system-linux",
        "real_result": true
      },
      {
        "title": "Operační systém Linux (TIPY A Triky) | Alza.cz",
        "href": "https://www.alza.cz/operacni-system-linux",
        "real_result": true
      },
      {
        "title": "Linux (jádro) – Wikipedie",
        "href": "https://cs.wikipedia.org/wiki/Linux_(j%C3%A1dro)",
        "real_result": true
      },
      {
        "title": "O čem je Linux a jakou distribuci si vybrat?",
        "href": "https://www.zive.cz/clanky/o-cem-je-linux-a-jakou-distribuci-si-vybrat/sc-3-a-140304/default.aspx",
        "real_result": true
      },
      {
        "title": "Operační systém Linux pod drobnohledem, Windows se třese strachy",
        "href": "https://www.novinky.cz/clanek/internet-a-pc-software-operacni-system-linux-pod-drobnohledem-windows-se-trese-strachy-40224051",
        "real_result": true
      }
    ],
    "user": "anon_dp_tool",
    "timestamp": "2024-03-26T08:22:52.646Z"
  },
  {
    "query": "kempování v přírodě",
    "language": "queries",
    "results": [
      {
        "title": "Jak legálně přespat v přírodě - Slovensko | 4Camping.cz",
        "href": "https://www.4camping.cz/clanky/poradna/jak-legalne-prespat-v-prirode-jedeme-na-slovensko/",
        "real_result": true
      },
      {
        "title": "Kempování v ČR - Kempování u majitelů pozemku",
        "href": "https://www.bezkempu.cz/mapa",
        "real_result": true
      },
      {
        "title": "Turistika a kemping MTBIKER.cz - Vše pro turistiku a kempování",
        "href": "https://www.mtbiker.cz/shop/outdoor/turistika-a-kemping",
        "real_result": true
      },
      {
        "title": "Kemping v přírodě a vybavení na něj - ISIC.cz",
        "href": "https://www.isic.cz/clanek/cestovani/kemping-v-prirode-a-vybaveni-na-nej/",
        "real_result": true
      },
      {
        "title": "Kempování nadivoko: Ušetříte, ale pozor na zákony. Jak bez obav trávit čas v české přírodě?",
        "href": "https://cnn.iprima.cz/kempovani-na-divoko-usetrite-ale-pozor-na-zakony-jak-travit-cas-v-ceske-prirode-371826",
        "real_result": true
      },
      {
        "title": "Obrázky›Kempování v přírodě",
        "href": "/obrazky/?q=kempov%C3%A1n%C3%AD+v+p%C5%99%C3%ADrod%C4%9B&fulltext=&sourceid=fulltext&thru=hint-obrazky-super#utm_content=super&utm_term=kempov%C3%A1n%C3%AD%20v%20p%C5%99%C3%ADrod%C4%9B&utm_medium=hint&utm_source=search.seznam.cz",
        "real_result": false
      },
      {
        "title": "Kempování v přírodě: 8 důvodů proč letos vyrazit za…",
        "href": "https://www.alpinepro.cz/kempovani-v-prirode-8-duvodu-proc-letos-vyrazit-za-dobrodruzstvim/",
        "real_result": true
      },
      {
        "title": "Kempy nejsou nic pro vás? Známe nejlepší místa na stanování v…",
        "href": "https://www.tulenipasy.cz/skialpinismus-39710-kempy-nejsou-nic-pro-vas-zname-nejlepsi-mista-na-stanovani-v-ceske-prirode/",
        "real_result": true
      },
      {
        "title": "Kempink.cz - kompletní vybavení kempů a chat",
        "href": "https://www.kempink.cz/",
        "real_result": true
      },
      {
        "title": "Stanování a Bivakování v ČR - Kde a Jak? [RADY OD Expertů…",
        "href": "https://www.hudy.cz/stanovani-a-bivakovani-v-cr",
        "real_result": true
      },
      {
        "title": "Luxusní kempování neboli glamping | Blog Invia.cz",
        "href": "https://www.invia.cz/blog/luxusni-kempovani-neboli-glamping/",
        "real_result": true
      },
      {
        "title": "Zboží.cz›Kempování v přírodě",
        "href": "https://www.zbozi.cz/hledej/?q=kempov%C3%A1n%C3%AD%20v%20p%C5%99%C3%ADrod%C4%9B#utm_source=search.seznam.cz&utm_medium=hint&utm_content=products-opesBB&utm_ab=3178%2F5828%2C3122%2F5728%2C3121%2F5726%2C3166%2F5790%2C3120%2F5725%2C3179%2F5830&utm_term=kempov%C3%A1n%C3%AD%20v%20p%C5%99%C3%ADrod%C4%9B&utm_query=kempov%C3%A1n%C3%AD%20v%20p%C5%99%C3%ADrod%C4%9B",
        "real_result": false
      },
      {
        "title": "Dovolená pod stanem? 10 nejlepších kempů v Česku!",
        "href": "https://www.blesk.cz/clanek/cestovani-cestujeme-po-cr/315404/dovolena-pod-stanem-10-nejlepsich-kempu-v-cesku.html",
        "real_result": true
      },
      {
        "title": "Glamping v Česku: 25 tipů na luxusní kempování - Cestolino.cz",
        "href": "https://www.cestolino.cz/magazin/d/glamping-v-cesku-25-tipu-na-luxusni-kempovani/",
        "real_result": true
      },
      {
        "title": "Kempy nabízí kvalitní ubytování za nízké ceny – Kudy z nudy",
        "href": "https://www.kudyznudy.cz/aktuality/ubytovani/kempy",
        "real_result": true
      },
      {
        "title": "Vybavení na kempování v akci - SPORTISIMO - 100+ prodejen",
        "href": "https://www.sportisimo.cz/camping-outdoor/",
        "real_result": true
      },
      {
        "title": "Venkovní hamaky - Špičkové outdoorové vybavení",
        "href": "https://hammock.cz/produkty/hamaky/",
        "real_result": true
      }
    ],
    "user": "anon_dp_tool",
    "timestamp": "2024-03-26T08:39:26.107Z"
  },
  {
    "query": "výletní loď",
    "language": "queries",
    "results": [
      {
        "title": "Luxusní plavby po světě - Nautyy.cz",
        "href": "https://www.nautyy.cz/",
        "real_result": true
      },
      {
        "title": "Na Vltavě - Lodě Praha 1 - Výletní plavba lodí a parníky",
        "href": "https://www.lode-praha.cz/vyhlidkove-plavby/",
        "real_result": true
      },
      {
        "title": "Výletní lodě parníky Praha 1 - Plavba po Vltavě výletní lodí",
        "href": "http://www.parniky-praha.eu/plavba-po-vltave/",
        "real_result": true
      },
      {
        "title": "Obrázky›Výletní loď",
        "href": "/obrazky/?q=v%C3%BDletn%C3%AD+lo%C4%8F&fulltext=&sourceid=fulltext&thru=hint-obrazky-carousel#utm_content=carousel&utm_term=v%C3%BDletn%C3%AD%20lo%C4%8F&utm_medium=hint&utm_source=search.seznam.cz",
        "real_result": false
      },
      {
        "title": "Výletní loď – Wikipedie",
        "href": "https://cs.wikipedia.org/wiki/V%C3%BDletn%C3%AD_lo%C4%8F",
        "real_result": true
      },
      {
        "title": "Nová největší výletní loď světa: Oslní vodním parkem, pojme osm tisíc lidí",
        "href": "https://tachovsky.denik.cz/zpravy-ze-sveta/nejvetsi-vyletni-lod-sveta-icon-of-the-seas.html",
        "real_result": true
      },
      {
        "title": "Videa›Výletní loď",
        "href": "//search.seznam.cz/videa/?q=v%C3%BDletn%C3%AD+lo%C4%8F#utm_content=organic&utm_term=v%C3%BDletn%C3%AD%20lo%C4%8F&utm_medium=hint&utm_source=search.seznam.cz",
        "real_result": false
      },
      {
        "title": "výletní lod – Heureka.cz",
        "href": "https://www.heureka.cz/?h%5Bfraze%5D=v%C3%BDletn%C3%AD+lod",
        "real_result": true
      },
      {
        "title": "Nová největší výletní loď světa vyplula. Je to monstrum pětkrát větší než legendární Titanic",
        "href": "https://www.autoforum.cz/predstaveni/nova-nejvetsi-vyletni-lod-sveta-vyplula-je-to-monstrum-petkrat-vetsi-nez-kdysi-rekordni-titanic/",
        "real_result": true
      },
      {
        "title": "Zažijte Prahu z jiné perspektivy!",
        "href": "https://www.vyletnilod.cz/",
        "real_result": true
      },
      {
        "title": "Nová největší výletní loď světa: Oslní vodním parkem, pojme osm tisíc lidí",
        "href": "https://www.denik.cz/ze_sveta/nejvetsi-vyletni-lod-sveta-icon-of-the-seas.html",
        "real_result": true
      },
      {
        "title": "Playmobil 6978 Výletní loď - Stavebnice | Alza.cz",
        "href": "https://www.alza.cz/hracky/playmobil-vyletni-lod-d4822209.htm",
        "real_result": true
      },
      {
        "title": "Nová éra luxusu na moři. Největší výletní loď světa poprvé vyplouvá",
        "href": "https://www.idnes.cz/zpravy/zahranicni/royal-caribbean-vyletni-lod-icon-of-the-seas-plavba-zazitek.A240127_202803_zahranicni_ikro",
        "real_result": true
      },
      {
        "title": "Extralife.cz – Jak vypadá největší výletní loď světa?",
        "href": "https://www.extralife.cz/jak-vypada-nejvetsi-vyletni-lod-sveta-ma-tisice-pokoju-i-vlastni-vodni-park_32092",
        "real_result": true
      },
      {
        "title": "Sestava Výletní lodě a parníky - zoroaster.cz",
        "href": "https://www.zoroaster.cz/kategorie/sestava-vyletni-lode-a-parniky/",
        "real_result": true
      },
      {
        "title": "Parníky a lodě Praha - Večírky, oslavy i lodní party",
        "href": "https://www.parnikypraha.cz/akce-na-lodi/",
        "real_result": true
      }
    ],
    "user": "anon_dp_tool",
    "timestamp": "2024-03-26T08:56:05.730Z"
  },
  {
    "query": "evropská liga",
    "language": "queries",
    "results": [
      {
        "title": "Evropská liga v TV na Telly - Sledujte ihned za 300 Kč",
        "href": "https://telly.cz/sport/",
        "real_result": true
      },
      {
        "title": "Evropská liga UEFA",
        "href": "/obrazky/?q=Evropsk%C3%A1+liga+UEFA#utm_content=leagueLeft&utm_term=evropská liga&utm_medium=hint&utm_source=search.seznam.cz",
        "real_result": false
      },
      {
        "title": "Čtvrtfinále Evropské ligy Leverkusen - West Ham nabídne i český souboj",
        "href": "https://www.ceskenoviny.cz/zpravy/2493153",
        "real_result": true
      },
      {
        "title": "Evropská liga UEFA 2022/2023 – Wikipedie",
        "href": "https://cs.wikipedia.org/wiki/Evropsk%C3%A1_liga_UEFA_2022/2023",
        "real_result": true
      },
      {
        "title": "Nejen Schick vs. Souček. Evropská liga nabídne velký český souboj",
        "href": "https://www.idnes.cz/fotbal/pohary/los-ctvrtfinale-evropska-liga-leverkusen-west-ham.A240315_134451_fot_pohary_ten",
        "real_result": true
      },
      {
        "title": "Evropská liga UEFA 2023/2024 – Wikipedie",
        "href": "https://cs.wikipedia.org/wiki/Evropsk%C3%A1_liga_UEFA_2023/2024",
        "real_result": true
      },
      {
        "title": "Los Evropské ligy: Souboj Čechů ve čtvrtfinále! Liverpool jde na Atalantu",
        "href": "https://isport.blesk.cz/clanek/fotbal-evropske-pohary-evropska-liga/444770/los-el-online-kdo-ve-ctvrtfinale-ceka-west-ham-nebo-leverkusen.html",
        "real_result": true
      },
      {
        "title": "Evropská liga UEFA – Wikipedie",
        "href": "https://cs.wikipedia.org/wiki/Evropsk%C3%A1_liga_UEFA",
        "real_result": true
      },
      {
        "title": "Evropská liga UEFA 2020/2021 – Wikipedie",
        "href": "https://cs.wikipedia.org/wiki/Evropsk%C3%A1_liga_UEFA_2020/2021",
        "real_result": true
      },
      {
        "title": "Evropská liga UEFA 2019/2020 – Wikipedie",
        "href": "https://cs.wikipedia.org/wiki/Evropsk%C3%A1_liga_UEFA_2019/2020",
        "real_result": true
      },
      {
        "title": "Evropská liga UEFA 2023/2024: los, zápasy a tabulka",
        "href": "https://www.fotbalzpravy.cz/rubriky/pohary/evropska-liga/evropska-liga-uefa-los-zapasy-a-tabulka_1154.html",
        "real_result": true
      },
      {
        "title": "Evropská liga UEFA: Vše, co potřebuješ vědět! - KurzoveSazeni…",
        "href": "https://www.kurzovesazeni.com/evropska-liga-uefa-vse-co-potrebujes-vedet/",
        "real_result": true
      },
      {
        "title": "TV Prima online na Skylink - Vyzkoušej online TV",
        "href": "https://www.skylink.cz/vyzkousej",
        "real_result": true
      }
    ],
    "user": "anon_dp_tool",
    "timestamp": "2024-03-26T09:12:45.695Z"
  },
  {
    "query": "potřebná očkování pro cestování",
    "language": "queries",
    "results": [
      {
        "title": "Očkování před cestou do zahraničí",
        "href": "https://zdravi.euro.cz/clanky/ockovani-pred-cestou-do-zahranici/",
        "real_result": true
      },
      {
        "title": "Cestujete do exotických zemí? Jaká očkování byste měli zvážit…",
        "href": "https://www.jenprocestovatele.cz/cestujete-do-exotickych-zemi-jaka-ockovani-byste-meli-zvazit/",
        "real_result": true
      },
      {
        "title": "Plánujete exotickou dovolenou: jaká očkování jsou potřeba…",
        "href": "https://www.webozdravi.cz/planujete-exotickou-dovolenou-myslete-take-na-ockovani/",
        "real_result": true
      },
      {
        "title": "Velký přehled očkování do zahraničí",
        "href": "https://www.vitalia.cz/clanky/ockovani-do-zahranici/",
        "real_result": true
      },
      {
        "title": "Všeobecná doporučení před cestou - Centrum cestovní medicíny",
        "href": "https://centrumcestovnimediciny.cz/vseobecna-doporuceni-pred-cestou/",
        "real_result": true
      },
      {
        "title": "Očkování při cestách do zahraničí | NZIP",
        "href": "https://www.nzip.cz/clanek/32-ockovani-do-zahranici",
        "real_result": true
      },
      {
        "title": "Očkování při cestách do zahraničí | Srovnejto.cz",
        "href": "https://www.srovnejto.cz/blog/ockovani-pri-cestach-do-zahranici-/",
        "real_result": true
      },
      {
        "title": "Očkování při cestách do zahraničí - SZÚ | Oficiální web…",
        "href": "https://szu.cz/temata-zdravi-a-bezpecnosti/cestovni-medicina/ockovani-do-zahranici/ockovani-pri-cestach-do-zahranici/",
        "real_result": true
      },
      {
        "title": "Doporučená očkování do zahraničí a exotických destinací",
        "href": "https://www.zdrave.cz/zdravy-zivot/doporucena-ockovani-do-zahranici-a-exotickych-destinaci/",
        "real_result": true
      },
      {
        "title": "Očkování na dovolenou: kam je skutečně potřeba?",
        "href": "https://www.tyden.cz/rubriky/zdravi/ockovani-na-dovolenou-kam-je-skutecne-potreba_207104.html",
        "real_result": true
      }
    ],
    "user": "anon_dp_tool",
    "timestamp": "2024-03-26T09:29:22.030Z"
  },
  {
    "query": "jak se naučit programovat",
    "language": "queries",
    "results": [
      {
        "title": "Chceš se naučit programovat? - Naučíme to i úplné začátečníky",
        "href": "https://engeto.cz/blog/programovani/programuju-1-jak-a-proc-zacit-s-programovanim/",
        "real_result": true
      },
      {
        "title": "Videa›Jak se naučit programovat",
        "href": "//search.seznam.cz/videa/?q=jak+se+nau%C4%8Dit+programovat#utm_content=organic&utm_term=jak%20se%20nau%C4%8Dit%20programovat&utm_medium=hint&utm_source=search.seznam.cz",
        "real_result": false
      },
      {
        "title": "Jak se naučit programovat | Programatori.cz",
        "href": "https://www.programatori.cz/blog/jak-se-naucit-programovat/",
        "real_result": true
      },
      {
        "title": "Jak se naučit programovat: návod pro začátečníky | Skillmea",
        "href": "https://skillmea.cz/blog/jak-se-naucit-programovat",
        "real_result": true
      },
      {
        "title": "Zboží.cz›Jak se naučit programovat",
        "href": "https:////www.zbozi.cz/hledej/?q=jak%20se%20nau%C4%8Dit%20programovat#utm_source=search.seznam.cz&utm_medium=hint&utm_content=products-opesBB&utm_ab=3166%2F5790%2C3120%2F5725%2C3179%2F5830%2C3178%2F5828%2C3122%2F5728%2C3121%2F5726&utm_term=jak%20se%20nau%C4%8Dit%20programovat&utm_query=jak%20se%20nau%C4%8Dit%20programovat",
        "real_result": false
      },
      {
        "title": "Jak se stát programátorem: Vše, co potřebujete vědět! | Blog…",
        "href": "https://orangeacademy.cz/clanky/jak-se-stat-programatorem/",
        "real_result": true
      },
      {
        "title": "Jak se naučit programovat",
        "href": "https://junior.guru/handbook/learn/",
        "real_result": true
      },
      {
        "title": "Jak se stát programátorem, průvodce pro začátečníky | Coders…",
        "href": "https://coderslab.cz/cz/blog/jak-se-stat-programatorem-pruvodce-pro-zacatecniky",
        "real_result": true
      },
      {
        "title": "5 způsobů, jak se naučit programovat",
        "href": "https://www.kurzy-programovani.cz/2021/06/pet-zpusobu-jak-se-naucit-programovat/",
        "real_result": true
      },
      {
        "title": "Programuju, 1. díl: Proč a jak se naučit programovat | Engeto",
        "href": "https://engeto.cz/blog/programovani/programuju-1-jak-a-proc-zacit-s-programovanim/",
        "real_result": true
      },
      {
        "title": "Jak se naučit programovat - kompletní průvodce - Bigg.cz - tipy…",
        "href": "https://bigg.cz/jak-se-naucit-programovat-kompletni-pruvodce/",
        "real_result": true
      },
      {
        "title": "Jak začít s programováním: Tipy pro úspěšný vstup do světa…",
        "href": "https://www.interval.cz/clanky/jak-zacit-s-programovanim-tipy-pro-uspesny-vstup-do-sveta-programovani/",
        "real_result": true
      },
      {
        "title": "Jak se naučit programovat v 10 lekcích - YouTube",
        "href": "https://www.youtube.com/watch?v=lrsXL1-0bkU",
        "real_result": true
      }
    ],
    "user": "anon_dp_tool",
    "timestamp": "2024-03-26T09:45:53.740Z"
  },
  {
    "query": "editor na programování",
    "language": "queries",
    "results": [
      {
        "title": "Naučíme tě programovat - Pro začátečníky i pokročilé",
        "href": "https://engeto.cz/prehled-kurzu/",
        "real_result": true
      },
      {
        "title": "PSPad - free unicode vývojářský textový editor určený pro HTML…",
        "href": "http://www.pspad.com/cz/",
        "real_result": true
      },
      {
        "title": "Komodo Edit: výborný editor pro webové programátory | Maxiorel…",
        "href": "https://www.maxiorel.cz/komodo-edit-vyborny-editor-pro-webove-programatory",
        "real_result": true
      },
      {
        "title": "Atom: VIMózní programátorský editor, který si prostě zamilujete…",
        "href": "https://www.maxiorel.cz/atom-vimozni-programatorsky-editor-ktery-si-proste-zamilujete",
        "real_result": true
      },
      {
        "title": "Textový editor VIM jako IDE - Pavel Tišnovský - Megaknihy.cz",
        "href": "https://www.megaknihy.cz/programovani/3216098-textovy-editor-vim-jako-ide.html",
        "real_result": true
      },
      {
        "title": "Webstorm ke stažení zdarma | Mujsoubor.cz - Programy a hry ke…",
        "href": "https://mujsoubor.cz/vyvojove-nastroje/webstorm",
        "real_result": true
      },
      {
        "title": "Program Edit - ihned zdarma ke stažení - Stahuj.cz",
        "href": "https://www.stahuj.cz/vyvojove_nastroje/multifunkcnieditory/program-edit/",
        "real_result": true
      },
      {
        "title": "Cimco Edit - světově nejznámější profesionální editor…",
        "href": "https://www.arkance-systems.cz/produkty/cimco-edit",
        "real_result": true
      },
      {
        "title": "HTML editory - Slunečnice.cz",
        "href": "https://www.slunecnice.cz/tvorba-webu-a-programovani/editory/",
        "real_result": true
      },
      {
        "title": "EditEx ke stažení zdarma - download",
        "href": "https://stahnu.cz/multifunkcni-editory/editex",
        "real_result": true
      },
      {
        "title": "Programmer's Wizard 2 - ihned zdarma ke stažení - Slunečnice.cz",
        "href": "https://www.slunecnice.cz/sw/programmers-wizard-2/",
        "real_result": true
      }
    ],
    "user": "anon_dp_tool",
    "timestamp": "2024-03-26T10:02:29.429Z"
  },
  {
    "query": "výsledky permier league",
    "language": "queries",
    "results": [
      {
        "title": "Sledujte Premier League online - CANAL+ sleduj Premier League",
        "href": "http://www.canalplussport.cz/nabidka",
        "real_result": true
      },
      {
        "title": "Premier League",
        "href": "/obrazky/?q=Premier+League#utm_content=leagueLeft&utm_term=výsledky premier league&utm_medium=hint&utm_source=search.seznam.cz",
        "real_result": false
      },
      {
        "title": "Premier League 2023/2024 výsledky - Fotbal/Anglie",
        "href": "https://www.livesport.cz/fotbal/anglie/premier-league/vysledky/",
        "real_result": true
      },
      {
        "title": "Premier League 2023/2024 tabulka - Fotbal/Anglie",
        "href": "https://www.livesport.cz/fotbal/anglie/premier-league/tabulka/",
        "real_result": true
      },
      {
        "title": "Premier League 2023/2024 live výsledky, Fotbal Anglie…",
        "href": "https://www.livesport.cz/fotbal/anglie/premier-league/",
        "real_result": true
      },
      {
        "title": "Premier League 2021/2022 výsledky - Fotbal/Anglie",
        "href": "https://www.livesport.cz/fotbal/anglie/premier-league-2021-2022/vysledky/",
        "real_result": true
      },
      {
        "title": "Premier League – tabulka, rozvrh a statistiky | Sofascore",
        "href": "https://www.sofascore.com/cs/soutez/fotbal/england/premier-league/17",
        "real_result": true
      },
      {
        "title": "Premier League 2023/2024: anglická liga - program a informace",
        "href": "https://www.betarena.cz/rubriky/sportovni-clanky/premier-league-anglicka-liga-program-a-informace_1473.html",
        "real_result": true
      },
      {
        "title": "Premier League 2020/21: informace, program, výsledky, tabulka",
        "href": "https://www.sazeni-online.eu/blog/premier-league-2020-21-informace-program-vysledky-tabulka",
        "real_result": true
      },
      {
        "title": "Anglická Premier League: informace, program zápasů a tabulka",
        "href": "https://www.fotbalzpravy.cz/rubriky/zahranici/anglie/anglicka-premier-league-informace-program-zapasu-a-tabulka_1076.html",
        "real_result": true
      },
      {
        "title": "Premier League 2023/24 | Tabulka",
        "href": "https://www.sport.cz/sekce/fotbal-premier-league-tabulky-708",
        "real_result": true
      },
      {
        "title": "Výsledky Premier League | Canal+ Sport",
        "href": "https://www.canalplussport.cz/premier-league/vysledky",
        "real_result": true
      },
      {
        "title": "Premier League - Výsledky, Tipy na sázky",
        "href": "https://www.tiptiket.cz/profil/fotbal/liga/english-premier-league",
        "real_result": true
      }
    ],
    "user": "anon_dp_tool",
    "timestamp": "2024-03-26T10:19:05.749Z"
  },
  {
    "query": "očkování asie",
    "language": "queries",
    "results": [
      {
        "title": "Očkování ASIE A Další Prevence | Cestopisný Deník",
        "href": "https://cestopisnydenik.cz/ockovani-do-zahranici-asie/",
        "real_result": true
      },
      {
        "title": "Chystáte se na exotickou dovolenou? Nezapomínejte na očkování…",
        "href": "https://www.newtravel.cz/clanky/exoticka-dovolena-ockovani/",
        "real_result": true
      },
      {
        "title": "Očkování při cestách do Asie, Kalimera",
        "href": "https://www.kalimera.cz/ockovani.html",
        "real_result": true
      },
      {
        "title": "Doporučená očkování do Střední Asie",
        "href": "https://www.ockovani-zahranici.cz/destinace/doporucena-ockovani-do-stredni-asie",
        "real_result": true
      },
      {
        "title": "Plánujete exotickou dovolenou: jaká očkování jsou potřeba…",
        "href": "https://www.webozdravi.cz/planujete-exotickou-dovolenou-myslete-take-na-ockovani/",
        "real_result": true
      },
      {
        "title": "Velký přehled: 7 očkování proti exotickým nemocem",
        "href": "https://www.vitalia.cz/clanky/ockovani-proti-exotickym-nemocem/",
        "real_result": true
      },
      {
        "title": "Rychlý přehled povinných a doporučených očkování do zahraničí…",
        "href": "https://www.zapakuj.cz/cestovatelske-tipy-triky/rychly-prehled-povinnych-a-doporucenych-ockovani-do-zahranici---nejen-zanzibar--sri-lanka-a-dominikanska-republika/",
        "real_result": true
      },
      {
        "title": "Zboží.cz›Očkování asie",
        "href": "https:////www.zbozi.cz/hledej/?q=o%C4%8Dkov%C3%A1n%C3%AD%20asie#utm_source=search.seznam.cz&utm_medium=hint&utm_content=products-opesBB&utm_ab=3178%2F5828%2C3122%2F5728%2C3121%2F5726%2C3166%2F5790%2C3120%2F5725%2C3179%2F5830&utm_term=o%C4%8Dkov%C3%A1n%C3%AD%20asie&utm_query=o%C4%8Dkov%C3%A1n%C3%AD%20asie",
        "real_result": false
      },
      {
        "title": "Asie, aktuální cestovní zdravotní rizika ve všech zemích",
        "href": "https://www.ockovacicentrum.cz/cz/asie",
        "real_result": true
      },
      {
        "title": "Cestujete do exotických zemí? Jaká očkování byste měli zvážit…",
        "href": "https://www.jenprocestovatele.cz/cestujete-do-exotickych-zemi-jaka-ockovani-byste-meli-zvazit/",
        "real_result": true
      },
      {
        "title": "Jak se očkuje ve světě: Indonésie řeší, jestli je vakcína halal…",
        "href": "https://plus.rozhlas.cz/jak-se-ockuje-ve-svete-indonesie-resi-jestli-je-vakcina-halal-a-izraelske-zasoby-8399573",
        "real_result": true
      }
    ],
    "user": "anon_dp_tool",
    "timestamp": "2024-03-26T10:35:40.353Z"
  },
  {
    "query": "Washington Capitals",
    "language": "queries",
    "results": [
      {
        "title": "Produkty Washington Capitals - Největší fanshop NHL v Evropě",
        "href": "https://www.fanda-nhl.cz/washington-capitals/",
        "real_result": true
      },
      {
        "title": "Washington Capitals",
        "href": "/obrazky/?q=Washington+Capitals#utm_content=teamLeft&utm_term=Washington Capitals&utm_medium=hint&utm_source=search.seznam.cz",
        "real_result": false
      },
      {
        "title": "Washington Capitals – Wikipedie",
        "href": "https://cs.wikipedia.org/wiki/Washington_Capitals#:~:text=Washington%20Capitals%20je%20profesion%C3%A1ln%C3%AD%20americk%C3%BD,jsou%20%C4%8Derven%C3%A1%2C%20modr%C3%A1%20a%20b%C3%ADl%C3%A1.",
        "real_result": true
      },
      {
        "title": "Washington Capitals - Wikipedia",
        "href": "https://en.wikipedia.org/wiki/Washington_Capitals",
        "real_result": true
      },
      {
        "title": "Ovečkin mění historii a tlačí Capitals do play off. V jedné kategorii ještě Jágr odolává",
        "href": "https://www.sport.cz/clanek/hokej-nhl-oveckin-meni-historii-a-tlaci-capitals-do-play-off-v-jedne-kategorii-jeste-jagr-odolava-5024892",
        "real_result": true
      },
      {
        "title": "Obrázky›Washington Capitals",
        "href": "/obrazky/?q=Washington+Capitals&fulltext=&sourceid=fulltext&thru=hint-obrazky-super#utm_content=super&utm_term=Washington%20Capitals&utm_medium=hint&utm_source=search.seznam.cz",
        "real_result": false
      },
      {
        "title": "Washington Capitals - wiki34.com",
        "href": "https://cs.wiki34.com/wiki/Washington_Capitals",
        "real_result": true
      },
      {
        "title": "Washington Capitals - Wikiwand",
        "href": "https://www.wikiwand.com/cs/Washington_Capitals",
        "real_result": true
      },
      {
        "title": "Edmonton Oilers vs Washington Capitals: NHL preview a tipy na sázení",
        "href": "https://www.ruik.cz/edmonton-oilers-vs-washington-capitals-nhl-preview-a-tipy-na-sazeni/",
        "real_result": true
      },
      {
        "title": "Washington Capitals - wiki7.org",
        "href": "https://cs.wiki7.org/wiki/%D0%92%D0%B0%D1%88%D0%B8%D0%BD%D0%B3%D1%82%D0%BE%D0%BD_%D0%9A%D1%8D%D0%BF%D0%B8%D1%82%D0%B0%D0%BB%D0%B7",
        "real_result": true
      },
      {
        "title": "Washington Capitals: Informace a soupiska",
        "href": "https://www.betarena.cz/rubriky/sportovni-clanky/washington-capitals-informace-a-soupiska_2791.html",
        "real_result": true
      },
      {
        "title": "Kategorie:Washington Capitals – Wikipedie",
        "href": "https://cs.wikipedia.org/wiki/Kategorie:Washington_Capitals",
        "real_result": true
      },
      {
        "title": "Nečasova dokonalost, Ovečkinovo svérázné vítání. Washington je záhada, která se rve o play off",
        "href": "https://www.sport.cz/clanek/hokej-nhl-necasova-dokonalost-oveckinovo-sverazne-vitani-washington-je-zahada-ktera-se-rve-o-play-off-5025134",
        "real_result": true
      }
    ],
    "user": "anon_dp_tool",
    "timestamp": "2024-03-26T10:52:13.366Z"
  },
  {
    "query": "css",
    "language": "queries",
    "results": [
      {
        "title": "CSS - Wikipedia",
        "href": "https://en.wikipedia.org/wiki/CSS",
        "real_result": true
      },
      {
        "title": "Centrum sociálních služeb Hrabyně",
        "href": "https://www.csshrabyne.cz/",
        "real_result": true
      },
      {
        "title": "Co je CSS? | Vojtěch Bruk",
        "href": "https://vojtechbruk.cz/pojem/css/",
        "real_result": true
      },
      {
        "title": "Úvod | Centrum sociálních služeb Ostrava, o.p.s.",
        "href": "https://css-ostrava.cz/",
        "real_result": true
      },
      {
        "title": "CSS – WikiKnihovna",
        "href": "https://wiki.knihovna.cz/index.php?title=CSS",
        "real_result": true
      },
      {
        "title": "CSS Tachov – Centrum sociálních služeb, Tachov. Příspěvková…",
        "href": "https://www.csstachov.cz/",
        "real_result": true
      },
      {
        "title": "CSS",
        "href": "https://www.helpmark.cz/slovnikpojmu/38-css",
        "real_result": true
      },
      {
        "title": "Css - wiki7.org",
        "href": "https://cs.wiki7.org/wiki/CSS",
        "real_result": true
      },
      {
        "title": "CSS - přehled CSS vlastností a hodnot",
        "href": "https://www.jakpsatweb.cz/css/css-vlastnosti-hodnoty-prehled.html",
        "real_result": true
      },
      {
        "title": "CSS – Wikislovník",
        "href": "https://cs.wiktionary.org/wiki/CSS",
        "real_result": true
      }
    ],
    "user": "anon_dp_tool",
    "timestamp": "2024-03-26T11:08:45.405Z"
  },
  {
    "query": "exotické dovolené",
    "language": "queries",
    "results": [
      {
        "title": "Exotická dovolená 2024 - Online ceny - ušetřete až 20%",
        "href": "https://www.edubai.cz/destinace",
        "real_result": true
      },
      {
        "title": "Poleťte s námi do exotiky - Dovolenou děláme s láskou",
        "href": "https://www.blue-style.cz/exoticka-dovolena/",
        "real_result": true
      },
      {
        "title": "Dovolená Exotika - levně - Dovolená 2024 v exotice",
        "href": "https://www.invia.cz/dovolena/exotika/",
        "real_result": true
      },
      {
        "title": "Odcestujte za exotikou - Dovolená od STUDENT AGENCY",
        "href": "https://dovolena.cz/exotika",
        "real_result": true
      },
      {
        "title": "Exotická dovolená – destinace, do kterých se vypravit",
        "href": "https://www.ervpojistovna.cz/cs/exoticka-dovolena",
        "real_result": true
      },
      {
        "title": "10 tipů, kam na exotickou dovolenou. Toto jsou TOP exotické…",
        "href": "https://www.kdyjet.cz/kam-na-exotickou-dovolenou/",
        "real_result": true
      },
      {
        "title": "Videa›Exotické dovolené",
        "href": "//search.seznam.cz/videa/?q=exotick%C3%A9+dovolen%C3%A9#utm_content=organic&utm_term=exotick%C3%A9%20dovolen%C3%A9&utm_medium=hint&utm_source=search.seznam.cz",
        "real_result": false
      },
      {
        "title": "Havaj - dovolená a poznávací zájezdy 2024 | CK SEN",
        "href": "https://www.cksen.cz/poznavaci-zajezdy/havaj/",
        "real_result": true
      },
      {
        "title": "Překvapivě blízká exotika: Tipy na levnou dovolenou v Evropě…",
        "href": "https://www.porovnej24.cz/clanky/prekvapive-blizka-exotika-aneb-tipy-levne-prazdninove-destinace",
        "real_result": true
      },
      {
        "title": "Exotická dovolená 2024 • CK Blue Style",
        "href": "https://www.blue-style.cz/exoticka-dovolena/",
        "real_result": true
      },
      {
        "title": "Tipy na exotickou dovolenou | New Travel.cz",
        "href": "https://www.newtravel.cz/clanky/tipy-na-exotickou-dovolenou/",
        "real_result": true
      },
      {
        "title": "Last, first minute 2023-2024 | dovolená u moře, | Rainbowtours…",
        "href": "https://rainbowtours.cz/stranky/exotika-2020-21-podminky-predprodeje",
        "real_result": true
      },
      {
        "title": "Last minute exotika: TOP destinace za super cenu | CK Fischer",
        "href": "https://www.fischer.cz/last-minute/exotika",
        "real_result": true
      },
      {
        "title": "Last minute exotická dovolená | EXIM tours",
        "href": "https://www.eximtours.cz/last-minute/exotika",
        "real_result": true
      },
      {
        "title": "Nejbližší a nejdostupnější exotické destinace | Blog Invia.cz",
        "href": "https://www.invia.cz/blog/nejblizsi-a-nejdostupnejsi-exoticke-destinace/",
        "real_result": true
      },
      {
        "title": "Dovolená v exotice od AIRSTOP - pomáháme Vám levněji cestovat",
        "href": "https://www.airstop.cz/",
        "real_result": true
      },
      {
        "title": "Exotická dovolená s NaCesty.cz - Specialista na německé CK",
        "href": "https://www.nacesty.cz/",
        "real_result": true
      },
      {
        "title": "Exotická dovolená s Čedokem - Zájezdy do všech koutů světa",
        "href": "https://www.cedok.cz/exoticke-koupani/",
        "real_result": true
      }
    ],
    "user": "anon_dp_tool",
    "timestamp": "2024-03-26T11:25:16.701Z"
  },
  {
    "query": "kurzy programování",
    "language": "queries",
    "results": [
      {
        "title": "Špičkový kurz Programátor - Praha - 22 dnů/150 hodin",
        "href": "https://www.primakurzy.cz/kurz-programovani/",
        "real_result": true
      },
      {
        "title": "Kurzy programování - Dotace ÚP až 50 000 Kč",
        "href": "https://coderslab.cz/cz/",
        "real_result": true
      },
      {
        "title": "Kurz programování - Více než 285+ online kurzů",
        "href": "https://skillmea.cz/online-kurzy/online/programovani",
        "real_result": true
      },
      {
        "title": "Rekvalifikační kurz v IT - Nastartujte kariéru ještě dnes",
        "href": "https://www.itnetwork.cz/prace-a-podnikani-v-it/rekvalifikacni-kurzy",
        "real_result": true
      },
      {
        "title": "Jak se naučit programovat v 10 lekcích | Agátin svět",
        "href": "https://www.agatinsvet.cz/jak-se-naucit-programovat-v-10-lekcich/",
        "real_result": true
      },
      {
        "title": "Online kurzy programování pro úplné začátečníky",
        "href": "https://www.kurzy-programovani.cz/",
        "real_result": true
      },
      {
        "title": "Kurzy programování nyní s certifikátem o absolvování",
        "href": "https://www.kurzy-programovani.cz/2023/01/kurzy-programovani-nyni-s-certifikatem-o-absolvovani/",
        "real_result": true
      },
      {
        "title": "Kurz: Jak se naučit programovat - Radek Kitner",
        "href": "https://kitner.cz/kurz/jak-se-naucit-programovat/",
        "real_result": true
      },
      {
        "title": "Kurzy programování – s lektorem online i prezenčně | Engeto",
        "href": "https://engeto.cz/prehled-kurzu/",
        "real_result": true
      },
      {
        "title": "Dá se naučit programování on-line? | Coders Lab IT Academy",
        "href": "https://coderslab.cz/cz/blog/je-mozne-naucit-se-programovani-online",
        "real_result": true
      },
      {
        "title": "Kurzy programování pro děti | CODE Rebels",
        "href": "https://www.coderebels.cz/",
        "real_result": true
      },
      {
        "title": "Seznam kurzů programování pro děti | CODE rebels",
        "href": "https://www.coderebels.cz/online-kurzy/",
        "real_result": true
      },
      {
        "title": "Kurz: Nauč se základy programování | Naučmese",
        "href": "https://www.naucmese.cz/kurz/nauc-se-zaklady-programovani",
        "real_result": true
      },
      {
        "title": "Kurzy Programování | EDU Trainings",
        "href": "https://edutrainings.cz/area/programovani/",
        "real_result": true
      },
      {
        "title": "Kurzy Programování - Cesta do světa programování",
        "href": "https://edutrainings.cz/area/programovani/",
        "real_result": true
      },
      {
        "title": "Kurzy programování Engeto - Pro začátečníky i pokročilé",
        "href": "https://engeto.cz/prehled-kurzu/",
        "real_result": true
      },
      {
        "title": "Kurz programování - katalog vzdělávacích kurzů",
        "href": "https://studium.cz/programovani-kurzy",
        "real_result": true
      }
    ],
    "user": "anon_dp_tool",
    "timestamp": "2024-03-26T11:42:00.861Z"
  },
  {
    "query": "html",
    "language": "queries",
    "results": [
      {
        "title": "Hypertext Markup Language – Wikipedie",
        "href": "https://cs.wikipedia.org/wiki/Hypertext_Markup_Language",
        "real_result": true
      },
      {
        "title": "Co je HTML? | Peach-dev",
        "href": "https://peach-dev.cz/wiki/html/",
        "real_result": true
      },
      {
        "title": "Pavel Szabo - Co je to HTML?",
        "href": "https://www.pavelszabo.cz/slovnik-pojmu-html/",
        "real_result": true
      },
      {
        "title": "HTML - Webfusion",
        "href": "https://webfusion.cz/slovnik/html/",
        "real_result": true
      },
      {
        "title": "HTML5 – Wikipedie",
        "href": "https://cs.wikipedia.org/wiki/HTML5",
        "real_result": true
      },
      {
        "title": "Co je html? | Vojtěch Bruk",
        "href": "https://vojtechbruk.cz/pojem/html/",
        "real_result": true
      },
      {
        "title": "HTML5: co přináší a proč se o něj zajímat",
        "href": "https://www.root.cz/clanky/html5-co-prinasi-a-proc-se-o-nej-zajimat/",
        "real_result": true
      },
      {
        "title": "Co je HTML",
        "href": "https://www.strafelda.cz/html",
        "real_result": true
      },
      {
        "title": "HTML | NetDirect.cz",
        "href": "https://www.netdirect.cz/clanek/685/html",
        "real_result": true
      },
      {
        "title": "HTML",
        "href": "https://online-antikvariat.cz/odborna-literatura/pocitace-a-internet/programovani/html",
        "real_result": true
      }
    ],
    "user": "anon_dp_tool",
    "timestamp": "2024-03-26T11:58:39.166Z"
  },
  {
    "query": "JavaScript",
    "language": "queries",
    "results": [
      {
        "title": "Learn JavaScript Online - Courses for Beginners - javascript…",
        "href": "https://www.javascript.com/",
        "real_result": true
      },
      {
        "title": "JavaScript – Wikipedie",
        "href": "https://cs.wikipedia.org/wiki/JavaScript",
        "real_result": true
      },
      {
        "title": "JavaScript - Wikipedia",
        "href": "https://en.wikipedia.org/wiki/JavaScript",
        "real_result": true
      },
      {
        "title": "JavaScript",
        "href": "https://www.tvorba-webu.cz/javascript/",
        "real_result": true
      },
      {
        "title": "Co je Javascript? | Peach-dev",
        "href": "https://peach-dev.cz/wiki/javascript/",
        "real_result": true
      },
      {
        "title": "JavaScript | VIP Trust s.r.o.",
        "href": "https://viptrust.com/technologie/programovaci-jazyky/javascript",
        "real_result": true
      },
      {
        "title": "JavaScript",
        "href": "https://www.upgates.cz/a/javascript",
        "real_result": true
      },
      {
        "title": "Co je Co je JavaScript?? | Vojtěch Bruk",
        "href": "https://vojtechbruk.cz/pojem/javascript/",
        "real_result": true
      },
      {
        "title": "Knihy „javascript“ – Heureka.cz",
        "href": "https://knihy.heureka.cz/f:q:javascript/",
        "real_result": true
      },
      {
        "title": "JavaScript - Memos Software",
        "href": "https://www.memos.cz/technologie/javascript/",
        "real_result": true
      },
      {
        "title": "Javascript pozice na míru - nabídky z Čech i Německa",
        "href": "https://talentpeople.cz/Kandidati",
        "real_result": true
      }
    ],
    "user": "anon_dp_tool",
    "timestamp": "2024-03-26T12:15:09.187Z"
  },
  {
    "query": "národní parky v čr",
    "language": "queries",
    "results": [
      {
        "title": "Národní parky ČR - Naučné karty",
        "href": "https://www.megaknihy.cz/priroda/250573-narodni-parky-cr-naucne-karty.html",
        "real_result": true
      },
      {
        "title": "Národní parky v Česku – Wikipedie",
        "href": "https://cs.wikipedia.org/wiki/N%C3%A1rodn%C3%AD_parky_v_%C4%8Cesku#:~:text=N%C3%A1rodn%C3%AD%20parky%20v%20%C4%8Cesku%20jsou,K%C5%99ivokl%C3%A1tsko%20a%20NP%20Soutok.%20Pro",
        "real_result": true
      },
      {
        "title": "Národní parky České Republiky | Cestovatelské tapas",
        "href": "https://www.cestovatelsketapas.cz/narodni-parky/",
        "real_result": true
      },
      {
        "title": "Obrázky›Národní parky v čr",
        "href": "/obrazky/?q=n%C3%A1rodn%C3%AD+parky+v+%C4%8Dr&fulltext=&sourceid=fulltext&thru=hint-obrazky-super#utm_content=super&utm_term=n%C3%A1rodn%C3%AD%20parky%20v%20%C4%8Dr&utm_medium=hint&utm_source=search.seznam.cz",
        "real_result": false
      },
      {
        "title": "Národní parky ČR: Poznejte je všechny | cKlub.cz",
        "href": "https://www.cklub.cz/blog/cestovatelske-tipy/narodni-parky-ceska",
        "real_result": true
      },
      {
        "title": "Národní parky a chráněná území v České republice",
        "href": "https://www.megaubytko.cz/narodni-parky-a-chranena-uzemi",
        "real_result": true
      },
      {
        "title": "Videa›Národní parky v čr",
        "href": "//search.seznam.cz/videa/?q=n%C3%A1rodn%C3%AD+parky+v+%C4%8Dr#utm_content=organic&utm_term=n%C3%A1rodn%C3%AD%20parky%20v%20%C4%8Dr&utm_medium=hint&utm_source=search.seznam.cz",
        "real_result": false
      },
      {
        "title": "Národní parky - Ministerstvo životního prostředí",
        "href": "https://www.mzp.cz/cz/narodni_parky",
        "real_result": true
      },
      {
        "title": "Národní parky ČR – Sportuj.com",
        "href": "https://www.sportuj.com/narodni-parky-cr/",
        "real_result": true
      },
      {
        "title": "České národní parky jsou ztělesněním krásné přírody. Co nabízejí?",
        "href": "https://www.novinky.cz/clanek/cestovani-co-nabizi-ceske-narodni-parky-40366098",
        "real_result": true
      },
      {
        "title": "Pramen Vltavy nebo nejvyšší hora v ČR. Krásy národních parků",
        "href": "https://www.seznamzpravy.cz/clanek/narodni-parky-cr-166990",
        "real_result": true
      },
      {
        "title": "Služby›Národní parky v čr",
        "href": "https://www.firmy.cz/sluzby/?q=n%c3%a1rodn%c3%ad%20parky%20v%20%c4%8dr&x=16.577500&y=49.167300&a=0.000000&utm_content=search-results&utm_term=n%c3%a1rodn%c3%ad%20parky%20v%20%c4%8dr&utm_medium=hint&utm_source=search.seznam.cz",
        "real_result": false
      },
      {
        "title": "Národní parky ČR: nejkrásnější místa a tipy na aktivity…",
        "href": "https://www.firmanazazitky.cz/blog/narodni-parky-cr-nejkrasnejsi-mista-a-tipy-na-aktivity",
        "real_result": true
      },
      {
        "title": "Kvíz: Co víte o českých národních parcích? Jsou čtyři a všechny jedinečné",
        "href": "https://www.prozeny.cz/clanek/kviz-kviz-co-vite-o-ceskych-narodnich-parcich-91006",
        "real_result": true
      }
    ],
    "user": "anon_dp_tool",
    "timestamp": "2024-03-26T12:31:43.722Z"
  },
  {
    "query": "Invia zájezdy",
    "language": "queries",
    "results": [
      {
        "title": "Invia - zájezdy levně - Nyní největší slevy",
        "href": "https://www.invia.cz/",
        "real_result": true
      },
      {
        "title": "Zájezdy s Čedokem - Zájezdy do všech koutů světa",
        "href": "https://www.cedok.cz/vysledky-vyhledavani/dovolena/",
        "real_result": true
      },
      {
        "title": "Ck Mayer&Crocus - Zájezdy - Specialista na poznávačky",
        "href": "https://www.poznavaci-zajezdy.cz/",
        "real_result": true
      },
      {
        "title": "Invia.cz - Vaše dovolená 2024, Nejširší výběr zájezdů od 300 CK",
        "href": "https://www.invia.cz/",
        "real_result": true
      },
      {
        "title": "Invia.cz, a.s. | Prodej zájezdů Praha - Nové Město - Najisto.cz",
        "href": "https://najisto.centrum.cz/288441/inviacz-as/",
        "real_result": true
      },
      {
        "title": "Invia - cestovní agentura - Info-Praha",
        "href": "https://www.info-praha.cz/inviacestovni-agentura10/index.html",
        "real_result": true
      },
      {
        "title": "Invia - cestovní agentura (Brno, Zábrdovice) • Firmy.cz",
        "href": "https://www.firmy.cz/detail/1351129-invia-cestovni-agentura-brno-zabrdovice.html",
        "real_result": true
      },
      {
        "title": "Poznávací zájezdy a dovolené s Invia.cz",
        "href": "https://www.invia.cz/poznavaci/",
        "real_result": true
      },
      {
        "title": "Invia - cestovní agentura - Info-Čechy",
        "href": "https://www.info-cechy.cz/inviacestovni-agentura/index.html",
        "real_result": true
      },
      {
        "title": "Zájezdy Invia International - Najdete pouze u Invia",
        "href": "https://www.invia.cz/slevy/najdete-pouze-u-invia/201-zajezdy-invia-international/",
        "real_result": true
      },
      {
        "title": "Invia – Wikipedie",
        "href": "https://cs.wikipedia.org/wiki/Invia",
        "real_result": true
      },
      {
        "title": "First Minute 2024 dovolená - Zájezdy se slevou za včasný nákup…",
        "href": "https://www.invia.cz/dovolena/first-minute/",
        "real_result": true
      },
      {
        "title": "LAST Minute zájezdy 2024 od 300 CK na jediném místě na Invia.cz",
        "href": "https://www.invia.cz/dovolena/last-minute/vsechny-lastminute/",
        "real_result": true
      },
      {
        "title": "Poznávací zájezdy - Za poznáním s českými průvodci",
        "href": "https://www.avetour.cz/",
        "real_result": true
      },
      {
        "title": "Zájezd - Nákup od ověřených prodejců",
        "href": "https://aukro.cz/vv/zajezd",
        "real_result": true
      }
    ],
    "user": "anon_dp_tool",
    "timestamp": "2024-03-26T12:48:19.839Z"
  },
  {
    "query": "Winnipeg Jets",
    "language": "queries",
    "results": [
      {
        "title": "Produkty Winnipeg Jets - Největší fanshop NHL v Evropě",
        "href": "https://www.fanda-nhl.cz/winnipeg-jets/",
        "real_result": true
      },
      {
        "title": "Winnipeg Jets - Edmonton - Sledujte živě a sázejte",
        "href": "https://www.tipsport.cz/kurzy/zapas/ledni-hokej-winnipeg-jets-edmonton-oilers/5600119",
        "real_result": true
      },
      {
        "title": "Winnipeg Jets",
        "href": "/obrazky/?q=Winnipeg+Jets#utm_content=teamLeft&utm_term=Winnipeg Jets&utm_medium=hint&utm_source=search.seznam.cz",
        "real_result": false
      },
      {
        "title": "Winnipeg Jets CTA",
        "href": "https://winnipegjetscta.com/",
        "real_result": true
      },
      {
        "title": "Winnipeg Jets – Wikipedie",
        "href": "https://cs.wikipedia.org/wiki/Winnipeg_Jets#:~:text=Winnipeg%20Jets%20je%20profesion%C3%A1ln%C3%AD%20kanadsk%C3%BD,jsou%20tmav%C4%9B%20modr%C3%A1%2C%20b%C3%ADl%C3%A1%2C%20ocelov%C3%A1",
        "real_result": true
      },
      {
        "title": "Obrázky›Winnipeg Jets",
        "href": "/obrazky/?q=Winnipeg+Jets&fulltext=&sourceid=fulltext&thru=hint-obrazky-super#utm_content=super&utm_term=Winnipeg%20Jets&utm_medium=hint&utm_source=search.seznam.cz",
        "real_result": false
      },
      {
        "title": "Winnipeg Jets (1972–1996) – Wikipedie",
        "href": "https://cs.wikipedia.org/wiki/Winnipeg_Jets_(1972%E2%80%931996)",
        "real_result": true
      },
      {
        "title": "Winnipeg Jets - Wikipedia",
        "href": "https://en.wikipedia.org/wiki/Winnipeg_Jets",
        "real_result": true
      },
      {
        "title": "Videa›Winnipeg Jets",
        "href": "//search.seznam.cz/videa/?q=Winnipeg+Jets#utm_content=organic&utm_term=Winnipeg%20Jets&utm_medium=hint&utm_source=search.seznam.cz",
        "real_result": false
      },
      {
        "title": "Winnipeg Jets - wikiital.com",
        "href": "https://cs.wikiital.com/wiki/Winnipeg_Jets",
        "real_result": true
      },
      {
        "title": "Winnipeg Jets -",
        "href": "https://cesko.wiki/Winnipeg_Jets/",
        "real_result": true
      },
      {
        "title": "Kategorie:Winnipeg Jets – Wikipedie",
        "href": "https://cs.wikipedia.org/wiki/Kategorie:Winnipeg_Jets",
        "real_result": true
      },
      {
        "title": "Střídající Mrázek přibrzdil kanonádu Los Angeles, Winnipeg rozstřílel Anaheim",
        "href": "https://www.ceskenoviny.cz/zpravy/2493414",
        "real_result": true
      },
      {
        "title": "Winnipeg Monarchs (WHL) – Wikipedie",
        "href": "https://cs.wikipedia.org/wiki/Winnipeg_Monarchs_(WHL)",
        "real_result": true
      },
      {
        "title": "Kategorie:Winnipeg Jets (1972–1996) – Wikipedie",
        "href": "https://cs.wikipedia.org/wiki/Kategorie:Winnipeg_Jets_(1972%E2%80%931996)",
        "real_result": true
      }
    ],
    "user": "anon_dp_tool",
    "timestamp": "2024-03-26T13:04:57.368Z"
  },
  {
    "query": "Rust",
    "language": "queries",
    "results": [
      {
        "title": "Růst – Wikipedie",
        "href": "https://cs.wikipedia.org/wiki/R%C5%AFst",
        "real_result": true
      },
      {
        "title": "Růst - dasbestelexikon.de",
        "href": "https://www.dasbestelexikon.de/cs/wiki/R%c5%afst",
        "real_result": true
      },
      {
        "title": "Hospodářský růst – Wikipedie",
        "href": "https://cs.wikipedia.org/wiki/Hospod%C3%A1%C5%99sk%C3%BD_r%C5%AFst",
        "real_result": true
      },
      {
        "title": "růst | Vševěd.cz",
        "href": "https://encyklopedie.vseved.cz/r%c5%afst",
        "real_result": true
      },
      {
        "title": "růst – Wikislovník",
        "href": "https://cs.wiktionary.org/wiki/r%C5%AFst",
        "real_result": true
      },
      {
        "title": "Růst člověka – Wikipedie",
        "href": "https://cs.wikipedia.org/wiki/R%C5%AFst_%C4%8Dlov%C4%9Bka#:~:text=R%C5%AFst%20%C4%8Dlov%C4%9Bka%20(hum%C3%A1nn%C3%AD%20r%C5%AFst)%20je,se%20postupn%C4%9B%20st%C3%A1v%C3%A1%20dosp%C4%9Bl%C3%BD%20%C4%8Dlov%C4%9Bk.",
        "real_result": true
      },
      {
        "title": "Růst – Wikicitáty",
        "href": "https://cs.wikiquote.org/wiki/R%C5%AFst",
        "real_result": true
      },
      {
        "title": "Růst - Novinky",
        "href": "https://www.novinky.cz/tag/rust-38146",
        "real_result": true
      },
      {
        "title": "Růst vlasů – jak rychle rostou a co jim pomáhá růst? - Plushair…",
        "href": "https://plushair.cz/blog/rust-vlasu-jak-rychle-rostou-a-co-pomaha-na-rust-vlasu/",
        "real_result": true
      },
      {
        "title": "Růst — ČT24 — Česká televize",
        "href": "https://ct24.ceskatelevize.cz/tema/rust-6328",
        "real_result": true
      }
    ],
    "user": "anon_dp_tool",
    "timestamp": "2024-03-26T13:21:34.686Z"
  },
  {
    "query": "kde se dá spát v autě",
    "language": "queries",
    "results": [
      {
        "title": "Videa›Kde se dá spát v autě",
        "href": "//search.seznam.cz/videa/?q=kde+se+d%C3%A1+sp%C3%A1t+v+aut%C4%9B#utm_content=organic&utm_term=kde%20se%20d%C3%A1%20sp%C3%A1t%20v%20aut%C4%9B&utm_medium=hint&utm_source=search.seznam.cz",
        "real_result": false
      },
      {
        "title": "Spaní v autě na divoko je čím dál oblíbenější. V Česku je ale takové přespávání trochu problém",
        "href": "https://auto-mania.cz/spani-v-aute-na-divoko-je-cim-dal-oblibenejsi-v-cesku-je-ale-takove-prespavani-trochu-problem/",
        "real_result": true
      },
      {
        "title": "Kde je možné přespat v autě a kde kempovat?",
        "href": "https://www.portalridice.cz/clanek/kde-je-mozne-prespat-v-aute-a-kde-kempovat",
        "real_result": true
      },
      {
        "title": "V jakých autech se dá vyrazit na cesty a spát v nich? Běžné modely, které nejsou sice určené k nocování, ale hravě obstojí",
        "href": "https://www.autozive.cz/auta-nocovani-bezne-modely/",
        "real_result": true
      },
      {
        "title": "Spaní v obytném autě a jak cestovat na divoko v ČR | Campiri…",
        "href": "https://www.campiri.com/cs-cz/spani-v-obytnem-aute-a-jak-cestovat-na-divoko-v-cr--clanek-77",
        "real_result": true
      },
      {
        "title": "Jak levně na dovolenou? Spát v autě se nesmí zdaleka všude! Někde za to hrozí tučné pokuty",
        "href": "https://www.garaz.cz/clanek/jak-levne-na-dovolenou-spat-v-aute-se-nesmi-zdaleka-vsude-21001513",
        "real_result": true
      },
      {
        "title": "JAK Přespat V AUTĚ?",
        "href": "https://auto-zuskarova.cz/jak-prespat-v-aute-",
        "real_result": true
      },
      {
        "title": "Evropou „na divoko“ aneb Spaní v autě není povoleno všude - AZ…",
        "href": "https://www.az-pneu.cz/clanky/Evropou-na-divoko-aneb-spani-v-aute-neni-povoleno-vsude",
        "real_result": true
      },
      {
        "title": "Spaní v autě: ustelte si pohodlně i na cestách | 4camping.cz",
        "href": "https://www.4camping.cz/clanky/poradna/spani-v-aute-ustelte-si-pohodlne-i-na-cestach/",
        "real_result": true
      },
      {
        "title": "Vše o spaní v autě a volném kempování: Kde je to možné? A kde naopak hrozí problémy?",
        "href": "https://www.auto.cz/vse-o-spani-v-aute-a-volnem-kempovani-kde-je-to-mozne-a-kde-naopak-hrozi-problemy-140300",
        "real_result": true
      },
      {
        "title": "Čeká vás cestou na dovolenou spaní v autě? Poradíme, jak si ho zpříjemnit",
        "href": "https://autoroad.cz/zajimavosti/87241-ceka-vas-cestou-na-dovolenou-spani-v-aute-poradime-jak-si-ho-zprijemnit",
        "real_result": true
      }
    ],
    "user": "anon_dp_tool",
    "timestamp": "2024-03-26T13:38:06.065Z"
  },
  {
    "query": "BRENNA letní dovolená",
    "language": "queries",
    "results": [
      {
        "title": "Letní dovolená 2024 - First Minute slevy až 50 %",
        "href": "https://dovolena.cz/first-minute",
        "real_result": true
      },
      {
        "title": "Letní dovolená v Česku - Více než 890 nabídek",
        "href": "https://travelking.cz/leto-v-cesku",
        "real_result": true
      },
      {
        "title": "Letní dovolená v Čechách - Zábava pro děti i pro rodiče",
        "href": "https://www.equitana.cz/pobytove-balicky",
        "real_result": true
      },
      {
        "title": "Letní dovolená s Čedokem - Zájezdy do všech koutů světa",
        "href": "https://www.cedok.cz/vysledky-vyhledavani/dovolena/",
        "real_result": true
      },
      {
        "title": "Letní dovolená 2024 | Brenna",
        "href": "https://www.brenna.cz/letni-dovolena",
        "real_result": true
      },
      {
        "title": "Dovolená LÉTO 2024 - Řecko, Bulharsko, Turecko a Egypt od…",
        "href": "https://www.brenna.cz/",
        "real_result": true
      },
      {
        "title": "Cestovní kancelář Brenna, s.r.o. | Letní dovolená a zimní…",
        "href": "https://najisto.centrum.cz/83243/brenna-sro/",
        "real_result": true
      },
      {
        "title": "Dovolená LÉTO 2024 | Brenna",
        "href": "https://www.brenna.cz/vyhledavani",
        "real_result": true
      },
      {
        "title": "Brenna, s.r.o. CK Brenna - Česká poradna",
        "href": "https://www.ceskaporadna.cz/profil/brenna-s-r-o-ck-brenna",
        "real_result": true
      },
      {
        "title": "First minute slevy | Brenna",
        "href": "https://www.brenna.cz/cestovni-kancelar-brenna/first-minute-slevy",
        "real_result": true
      },
      {
        "title": "Brenna - cestovní kancelář, Brno-střed • FirmyNaMorave.cz",
        "href": "https://www.firmynamorave.cz/detail/1518263-brenna-cestovni-kancelar",
        "real_result": true
      },
      {
        "title": "Cestovní kancelář Brenna - dovolena.cz",
        "href": "https://dovolena.cz/brenna",
        "real_result": true
      },
      {
        "title": "Cestovní kancelář Brenna tour | Evatour.cz",
        "href": "https://www.evatour.cz/stranky/1486:cestovni-kancelar-brenna-tour.html",
        "real_result": true
      },
      {
        "title": "Cestovní kancelář Brenna | Brenna",
        "href": "https://www.brenna.cz/cestovni-kancelar-brenna",
        "real_result": true
      },
      {
        "title": "Koupit Letní Dovolená 2024 - Letní Dovolená 2024",
        "href": "https://www.invia.cz/dovolena/",
        "real_result": true
      },
      {
        "title": "Dovolená přes AIRSTOP.CZ - pomáháme Vám levněji cestovat",
        "href": "https://www.airstop.cz/",
        "real_result": true
      },
      {
        "title": "Levná dovolená 2024 - First minute dovolená",
        "href": "https://skrz.cz/dovolena-more",
        "real_result": true
      }
    ],
    "user": "anon_dp_tool",
    "timestamp": "2024-03-26T13:54:37.518Z"
  },
  {
    "query": "Čedok zájezdy",
    "language": "queries",
    "results": [
      {
        "title": "Zájezdy přes AIRSTOP.CZ - pomáháme Vám levněji cestovat",
        "href": "https://www.airstop.cz/",
        "real_result": true
      },
      {
        "title": "Zájezdy přímo od Čedoku - Sezóna 2024 v prodeji",
        "href": "https://www.cedok.cz/",
        "real_result": true
      },
      {
        "title": "Čedok - last minute - pobytové i poznávací zájezdy - dovolená v…",
        "href": "https://www.cedok.cz/",
        "real_result": true
      },
      {
        "title": "Dovolená Čedok 2024 | Zájezdy.cz",
        "href": "https://www.zajezdy.cz/dovolena-cedok/",
        "real_result": true
      },
      {
        "title": "Sdovolená.cz›Tipy na   dovolenou  ",
        "href": "https://sdovolena.seznam.cz/search?company=5#source:hint-advert&utm_content=sdovolena&utm_term=%C4%8Cedok%20z%C3%A1jezdy&utm_medium=hint&utm_source=search.seznam.cz",
        "real_result": false
      },
      {
        "title": "Čedok a.s. - Česká poradna",
        "href": "https://www.ceskaporadna.cz/profil/cedok-a-s",
        "real_result": true
      },
      {
        "title": "Poznávací zájezdy Čedok 2024 | Zájezdy.cz",
        "href": "https://www.zajezdy.cz/poznavaci-cedok/",
        "real_result": true
      },
      {
        "title": "Čedok a.s., Žďár nad Sázavou - Žďár nad Sázavou 1…",
        "href": "https://www.zlatestranky.cz/profil/H62001",
        "real_result": true
      },
      {
        "title": "Čedok | Pražská Plynárenská",
        "href": "https://www.ppas.cz/zakaznicka-karta/cestovani-ubytovani/cedok",
        "real_result": true
      },
      {
        "title": "Výsledky Vyhledávání | Čedok a.s.",
        "href": "https://www.cedok.cz/last-minute?view=offerList&order=popular",
        "real_result": true
      },
      {
        "title": "Aktuální zájezdy Čedok, dovolená 2024/2025 - Cestolino.cz",
        "href": "https://www.cestolino.cz/dovolena/f/ck:70/",
        "real_result": true
      },
      {
        "title": "Česká republika od Čedok, dovolená 2024/2025 - Cestolino.cz",
        "href": "https://www.cestolino.cz/dovolena/cr/f/ck:70/",
        "real_result": true
      },
      {
        "title": "Výsledky Vyhledávání | Čedok a.s.",
        "href": "https://www.cedok.cz/cs/search-results/holidays/",
        "real_result": true
      },
      {
        "title": "CK AVETOUR - Poznávací zájezdy",
        "href": "https://www.avetour.cz/",
        "real_result": true
      },
      {
        "title": "Vaše Zájezdy 2024 až -50% - Hotely se slevou až 50 %",
        "href": "https://www.invia.cz/dovolena/",
        "real_result": true
      },
      {
        "title": "Německé cestovky v ČR - Dovolená od NaCesty.cz",
        "href": "https://www.nacesty.cz/",
        "real_result": true
      }
    ],
    "user": "anon_dp_tool",
    "timestamp": "2024-03-26T14:11:18.348Z"
  },
  {
    "query": "Viktoria Plzeň",
    "language": "queries",
    "results": [
      {
        "title": "FC Viktoria Plzeň",
        "href": "/obrazky/?q=FC+Viktoria+Plze%C5%88#utm_content=teamLeft&utm_term=Viktoria Plzeň&utm_medium=hint&utm_source=search.seznam.cz",
        "real_result": false
      },
      {
        "title": "FC Viktoria Plzeň",
        "href": "https://fcviktoria.cz/",
        "real_result": true
      },
      {
        "title": "FC Viktoria Plzeň, a.s. - Plzeň | netkatalog.cz",
        "href": "https://www.netkatalog.cz/firma/329785-fc-viktoria-plzen-as/",
        "real_result": true
      },
      {
        "title": "FC Viktoria Plzeň – Wikipedie",
        "href": "https://cs.wikipedia.org/wiki/FC_Viktoria_Plze%C5%88",
        "real_result": true
      },
      {
        "title": "FC Viktoria Plzeň , a.s., Plzeň, Východní Předměstí - Živéfirmy…",
        "href": "https://www.zivefirmy.cz/fc-viktoria-plzen_f1188819",
        "real_result": true
      },
      {
        "title": "Plzeň dostala od UEFA za vhozený kelímek pokutu a dvouletou podmínku",
        "href": "https://www.ceskenoviny.cz/zpravy/2495731",
        "real_result": true
      },
      {
        "title": "Videa›Viktoria Plzeň",
        "href": "//search.seznam.cz/videa/?q=Viktoria+Plze%C5%88#utm_content=organic&utm_term=Viktoria%20Plze%C5%88&utm_medium=hint&utm_source=search.seznam.cz",
        "real_result": false
      },
      {
        "title": "FC Viktoria Plzeň v evropských fotbalových pohárech – Wikipedie",
        "href": "https://cs.wikipedia.org/wiki/FC_Viktoria_Plze%C5%88_v_evropsk%C3%BDch_fotbalov%C3%BDch_poh%C3%A1rech",
        "real_result": true
      },
      {
        "title": "FC Viktoria Plzeň | Česko-Katalog.cz",
        "href": "http://www.cesko-katalog.cz/firma/199522/fc-viktoria-plzen-as.html",
        "real_result": true
      },
      {
        "title": "FC Viktoria Plzeň - zápasy, program a výsledky",
        "href": "https://www.fotbalzpravy.cz/rubriky/cesko/plzen/fc-viktoria-plzen-zapasy-program-a-vysledky_1066.html",
        "real_result": true
      },
      {
        "title": "Obrázky›Viktoria Plzeň",
        "href": "/obrazky/?q=Viktoria+Plze%C5%88&fulltext=&sourceid=fulltext&thru=hint-obrazky-super#utm_content=super&utm_term=Viktoria%20Plze%C5%88&utm_medium=hint&utm_source=search.seznam.cz",
        "real_result": false
      },
      {
        "title": "FC Viktoria Plzeň | Plzeň - katalog firem",
        "href": "http://www.plzen-katalog.cz/firma/199522/fc-viktoria-plzen-as.html",
        "real_result": true
      },
      {
        "title": "Viktoria zaplatí za vhozený kelímek tučnou pokutu, hrozilo i uzavření tribuny",
        "href": "https://plzensky.denik.cz/fotbal-prvni-liga/viktoria-zaplati-kelimek-tucna-pokuta-hrozilo-i-uzavreni-tribuny-202.html",
        "real_result": true
      },
      {
        "title": "Viktoria Plzeň - Výsledky, Tipy na sázky",
        "href": "https://www.tiptiket.cz/profil/fotbal/tym/fc-viktoria-plzen",
        "real_result": true
      }
    ],
    "user": "anon_dp_tool",
    "timestamp": "2024-03-26T14:27:58.340Z"
  },
  {
    "query": "kde je povoleno kempování",
    "language": "queries",
    "results": [
      {
        "title": "Kempování v ČR - Kempování u majitelů pozemku",
        "href": "https://www.bezkempu.cz/mapa",
        "real_result": true
      },
      {
        "title": "Turistika a kemping MTBIKER.cz - Vše pro turistiku a kempování",
        "href": "https://www.mtbiker.cz/shop/outdoor/turistika-a-kemping",
        "real_result": true
      },
      {
        "title": "Kde je povolene stanovat - Travelology",
        "href": "https://travelology.cz/cestovani/stanovani/kde-je-povolene-stanovat/",
        "real_result": true
      },
      {
        "title": "Stanování ve volné přírodě: Kde v Evropě je zakázáno nocovat…",
        "href": "https://www.cklub.cz/blog/lowcost-cestovani/stanovani-ve-volne-prirode-kde-v-evrope-je-zakazano-nocovat-mimo-kempy",
        "real_result": true
      },
      {
        "title": "Vyrazíte na dovolenou obytňákem? Víte, kde můžete volně přespat, a kde nikoliv?",
        "href": "https://auto-mania.cz/vyrazite-na-dovolenou-obytnakem-vite-kde-muzete-volne-prespat-a-kde-nikoliv/",
        "real_result": true
      },
      {
        "title": "Kde můžete kempovat na divoko a kde je freekemping zakázaný…",
        "href": "https://www.vansafe.cz/clanky-o-karavaningu-a-cestovani/v-jakych-zemich-muzete-kempovat-na-divoko",
        "real_result": true
      },
      {
        "title": "Kempování na divoko - jak to chodí v Evropě",
        "href": "https://topdovca.cz/blog/kempovani-na-divoko-v-evrope",
        "real_result": true
      },
      {
        "title": "Evropa - přehled zemí - kempování na divoko - All4Camper",
        "href": "https://all4camper.com/cs/evropa-prehled-zemi-kempovani-na-divoko/",
        "real_result": true
      },
      {
        "title": "Kempy nejsou nic pro vás? Známe nejlepší místa na stanování v…",
        "href": "https://www.tulenipasy.cz/skialpinismus-39710-kempy-nejsou-nic-pro-vas-zname-nejlepsi-mista-na-stanovani-v-ceske-prirode/",
        "real_result": true
      },
      {
        "title": "Stanování a Bivakování v ČR - Kde a Jak? [RADY OD Expertů…",
        "href": "https://www.hudy.cz/stanovani-a-bivakovani-v-cr",
        "real_result": true
      },
      {
        "title": "Dovolená pod stanem má svoje kouzlo - Cestujeme českem",
        "href": "https://cestujemeceskem.cz/dovolena-pod-stanem-ma-svoje-kouzlo/",
        "real_result": true
      },
      {
        "title": "Dovolená pod stanem? 10 nejlepších kempů v Česku!",
        "href": "https://www.blesk.cz/clanek/cestovani-cestujeme-po-cr/315404/dovolena-pod-stanem-10-nejlepsich-kempu-v-cesku.html",
        "real_result": true
      },
      {
        "title": "Vybavení na kempování v akci - SPORTISIMO - 100+ prodejen",
        "href": "https://www.sportisimo.cz/camping-outdoor/",
        "real_result": true
      }
    ],
    "user": "anon_dp_tool",
    "timestamp": "2024-03-26T14:44:37.525Z"
  },
  {
    "query": "solo cestování",
    "language": "queries",
    "results": [
      {
        "title": "Osamělé dobrodružství: Proč solo cestování stojí za to…",
        "href": "https://traveluj.cz/blog/osamele-dobrodruzstvi-proc-solo-cestovani-stoji-za-to/",
        "real_result": true
      },
      {
        "title": "Single zájezdy pro svobodné cestování | Invia.cz",
        "href": "https://www.invia.cz/dovolena/single-dovolena/",
        "real_result": true
      },
      {
        "title": "Výhody a nevýhody solo cestování – Teru Menclová",
        "href": "http://terusguide.com/solo-cestovani/",
        "real_result": true
      },
      {
        "title": "Zboží.cz›Solo cestování",
        "href": "https://www.zbozi.cz/hledej/?q=solo%20cestov%C3%A1n%C3%AD#utm_source=search.seznam.cz&utm_medium=hint&utm_content=products-opesBB&utm_ab=3179%2F5830%2C3178%2F5828%2C3122%2F5728%2C3121%2F5726%2C3166%2F5790%2C3120%2F5725&utm_term=solo%20cestov%C3%A1n%C3%AD&utm_query=solo%20cestov%C3%A1n%C3%AD",
        "real_result": false
      },
      {
        "title": "Solo cestování světem - Simona Holešínská",
        "href": "https://www.vizazistkasimona.cz/cestovani-o-samote/",
        "real_result": true
      },
      {
        "title": "Sólo cestování: nebojte se vyrazit sami! | Top-ArmyShop.cz",
        "href": "https://www.top-armyshop.cz/magazin/solo-cestovani-nebojte-se-vyrazit-sami",
        "real_result": true
      },
      {
        "title": "Videa›Solo cestování",
        "href": "//search.seznam.cz/videa/?q=solo+cestov%C3%A1n%C3%AD#utm_content=organic&utm_term=solo%20cestov%C3%A1n%C3%AD&utm_medium=hint&utm_source=search.seznam.cz",
        "real_result": false
      },
      {
        "title": "Sólo cestování není samota, ale sebepoznání | Camping-outdoor…",
        "href": "https://www.camping-outdoor.cz/solo-cestovani-neni-samota-ale-sebepoznani/",
        "real_result": true
      },
      {
        "title": "Singles Collection - pro sólo cestovatele - Marco Polo…",
        "href": "https://www.marco-polo.cz/zazitek/singles",
        "real_result": true
      },
      {
        "title": "Sólo cestování přináší spoustu výhod. Je ale bezpečné…",
        "href": "https://magazincestovatel.cz/tipy-a-rady/350-solo-cestovani-prinasi-spoustu-vyhod-je-ale-bezpecne",
        "real_result": true
      },
      {
        "title": "Sólo cestování: Proč ho singles milují a čemu na cestách čelí – Lifee.cz",
        "href": "https://www.lifee.cz/cestovani/solo-cestovani-proc-ho-singles-miluji-a-cemu-na-cestach-celi_61446.html",
        "real_result": true
      },
      {
        "title": "Společné cestování - Hyperinzerce.cz",
        "href": "https://seznamka.hyperinzerce.cz/seznamka-cestovani",
        "real_result": true
      }
    ],
    "user": "anon_dp_tool",
    "timestamp": "2024-03-26T15:01:12.475Z"
  },
  {
    "query": "výhodně cestovní pojištění",
    "language": "queries",
    "results": [
      {
        "title": "Cestovní pojištění | 50% sleva - Sjednání online za 2-3 minuty",
        "href": "https://www.axa-assistance.cz/cestovni-pojisteni/",
        "real_result": true
      },
      {
        "title": "ERV: Evropská pojišťovna - Cestovní pojištění na míru",
        "href": "https://online.ervpojistovna.cz/cestovni-pojisteni-online/volba-pojisteni.html",
        "real_result": true
      },
      {
        "title": "Cestovní pojištění online - sleva na pojištění až 50 %",
        "href": "https://www.epojisteni.cz/cestovni-pojisteni/",
        "real_result": true
      },
      {
        "title": "Cestovni pojisteni - Rychlý výsledek do 2 minut",
        "href": "https://www.srovnejto.cz/cestovni-pojisteni-online/",
        "real_result": true
      },
      {
        "title": "Cestovní pojištění – Wikipedie",
        "href": "https://cs.wikipedia.org/wiki/Cestovn%C3%AD_poji%C5%A1t%C4%9Bn%C3%AD",
        "real_result": true
      },
      {
        "title": "Cestovní pojištění online se slevou | Generali Česká pojišťovna",
        "href": "https://www.generaliceska.cz/cestovni-pojisteni",
        "real_result": true
      },
      {
        "title": "Výhodné cestovní pojištění pro Vaši dovolenou | CA FAST Travel",
        "href": "https://www.fasttravel.cz/cestovni-pojisteni",
        "real_result": true
      },
      {
        "title": "Nejlevnejší cestovní pojištění na cesty do zahraničí…",
        "href": "https://www.srovnejto.cz/nejlevnejsi-cestovni-pojisteni/",
        "real_result": true
      },
      {
        "title": "Nejlevnější cestovní pojištění | Top-Pojištění.cz (R)",
        "href": "https://www.top-pojisteni.cz/cestovni-pojisteni/nejlevnejsi-cestovni-pojisteni",
        "real_result": true
      },
      {
        "title": "Cestovní pojištění | CK České kormidlo",
        "href": "https://ceskekormidlo.cz/pojisteni/",
        "real_result": true
      },
      {
        "title": "Výhodné cestovní pojištění - VZP ČR",
        "href": "https://www.vzp.cz/pojistenci/vyhody-a-prispevky/darci/vyhodne-cestovni-pojisteni",
        "real_result": true
      },
      {
        "title": "Cestovní pojištění | Porovnej24.cz",
        "href": "https://www.porovnej24.cz/cestovni-pojisteni",
        "real_result": true
      },
      {
        "title": "cestovní pojištění – Heureka.cz",
        "href": "https://www.heureka.cz/?h%5Bfraze%5D=cestovn%C3%AD+poji%C5%A1t%C4%9Bn%C3%AD",
        "real_result": true
      },
      {
        "title": "Cestovní pojištění | Cruise Plus - umíme plavby po celém světě…",
        "href": "https://www.cruiseplus.cz/cestovni-pojisteni",
        "real_result": true
      },
      {
        "title": "Cestovní pojištění Kooperativa - Pojištění již od 16 Kč za den",
        "href": "https://www.koop.cz/cestovni-pojisteni",
        "real_result": true
      },
      {
        "title": "Cestovní pojištění sleva 55% - Pojištění do zahraničí",
        "href": "https://cestovni.yespojisteni.cz/",
        "real_result": true
      },
      {
        "title": "Akce: Cestovní pojištění 2024 - Nyní online sleva až 50 %",
        "href": "https://www.top-pojisteni.cz/cestovni-pojisteni",
        "real_result": true
      }
    ],
    "user": "anon_dp_tool",
    "timestamp": "2024-03-26T15:17:48.169Z"
  },
  {
    "query": "Ottawa Senators",
    "language": "queries",
    "results": [
      {
        "title": "Produkty Ottawa Senators - NHL Fan Shop | Fanda-NHL.cz",
        "href": "https://www.fanda-nhl.cz/ottawa-senators/",
        "real_result": true
      },
      {
        "title": "Ottawa Senators",
        "href": "/obrazky/?q=Ottawa+Senators#utm_content=teamLeft&utm_term=Ottawa Senators&utm_medium=hint&utm_source=search.seznam.cz",
        "real_result": false
      },
      {
        "title": "Ottawa Senators – Wikipedie",
        "href": "https://cs.wikipedia.org/wiki/Ottawa_Senators#:~:text=Ottawa%20Senators%20(francouzsky%20S%C3%A9nateurs%20d'Ottawa)%2C,kapacitou%2019%20153%20div%C3%A1k%C5%AF.%20Klubov%C3%A9",
        "real_result": true
      },
      {
        "title": "Obrázky›Ottawa Senators",
        "href": "/obrazky/?q=Ottawa+Senators&fulltext=&sourceid=fulltext&thru=hint-obrazky-super#utm_content=super&utm_term=Ottawa%20Senators&utm_medium=hint&utm_source=search.seznam.cz",
        "real_result": false
      },
      {
        "title": "Ottawa Senators (1893–1934) – Wikipedie",
        "href": "https://cs.wikipedia.org/wiki/Ottawa_Senators_(1893%E2%80%931934)",
        "real_result": true
      },
      {
        "title": "Ottawa Senators - Wikipedia",
        "href": "https://en.wikipedia.org/wiki/Ottawa_Senators",
        "real_result": true
      },
      {
        "title": "Videa›Ottawa Senators",
        "href": "//search.seznam.cz/videa/?q=Ottawa+Senators#utm_content=organic&utm_term=Ottawa%20Senators&utm_medium=hint&utm_source=search.seznam.cz",
        "real_result": false
      },
      {
        "title": "Ottawa Senators -",
        "href": "https://cesko.wiki/Ottawa_Senators/",
        "real_result": true
      },
      {
        "title": "Ottawa Senators (original) - Wikipedia",
        "href": "https://en.wikipedia.org/wiki/Ottawa_Senators_(original)",
        "real_result": true
      },
      {
        "title": "Ottawa Senators - dasbestelexikon.de",
        "href": "https://www.dasbestelexikon.de/cs/wiki/Ottawa_Senators",
        "real_result": true
      },
      {
        "title": "Kategorie:Ottawa Senators – Wikipedie",
        "href": "https://cs.wikipedia.org/wiki/Kategorie:Ottawa_Senators",
        "real_result": true
      },
      {
        "title": "Soubor:Original Ottawa Senators Logo.png – Wikipedie",
        "href": "https://cs.wikipedia.org/wiki/Soubor:Original_Ottawa_Senators_Logo.png",
        "real_result": true
      },
      {
        "title": "Ottawa Senators - Aktuálně.cz",
        "href": "https://www.aktualne.cz/ottawa-senators/l~i:keyword:63877/",
        "real_result": true
      },
      {
        "title": "Ottawa Senators | Hokej.cz - web českého hokeje",
        "href": "https://www.hokej.cz/klub/ottawa-senators/1998",
        "real_result": true
      }
    ],
    "user": "anon_dp_tool",
    "timestamp": "2024-03-26T15:34:29.908Z"
  }
]