[
  {
    "query": "HC VERVA Litvínov",
    "language": "queries",
    "results": [
      {
        "title": "HC Verva Litvínov",
        "href": "/obrazky/?q=HC+Verva+Litv%C3%ADnov#utm_content=teamLeft&utm_term=HC VERVA Litvínov&utm_medium=hint&utm_source=search.seznam.cz",
        "real_result": false
      },
      {
        "title": "HC Verva Litvínov",
        "href": "https://www.hcverva.cz/",
        "real_result": true
      },
      {
        "title": "HC Verva Litvínov | oficiální internetové stránky",
        "href": "https://hcltv.cz/",
        "real_result": true
      },
      {
        "title": "HC Verva Litvínov – Wikipedie",
        "href": "https://cs.wikipedia.org/wiki/HC_Verva_Litv%C3%ADnov",
        "real_result": true
      },
      {
        "title": "Hokejisté Pardubic zvládli i druhé semifinále, Litvínov porazili 3:0",
        "href": "https://www.ceskenoviny.cz/zpravy/2499660",
        "real_result": true
      },
      {
        "title": "HC Verva Litvínov , a.s., Litvínov, Horní Litvínov - Živéfirmy…",
        "href": "https://www.zivefirmy.cz/hc-verva-litvinov_f1378131",
        "real_result": true
      },
      {
        "title": "HC Verva Litvínov (ženy) – Wikipedie",
        "href": "https://cs.wikipedia.org/wiki/HC_Verva_Litv%C3%ADnov_(%C5%BEeny)",
        "real_result": true
      },
      {
        "title": "ANTOŠOVA BŘITVA: O přetrženém mozkovém propojení bráchů i o neférovém lynči deváťáků",
        "href": "https://www.sport.cz/clanek/hokej-extraliga-antosova-britva-o-pretrzenem-mozkovem-propojeni-brachu-i-o-neferovem-lynci-devataku-5025626",
        "real_result": true
      },
      {
        "title": "HC Verva Litvínov, a.s., IČO: 64048098 - rejstřík firem…",
        "href": "https://www.finmag.cz/obchodni-rejstrik/64048098-hc-verva-litvinov-a-s",
        "real_result": true
      },
      {
        "title": "HC Verva Litvínov, a.s. – Litvínov-Horní Litvínov | idatabaze…",
        "href": "https://www.idatabaze.cz/firma/198001-hc-verva-litvinov-as/",
        "real_result": true
      },
      {
        "title": "HC Verva Litvínov | Hokej.cz - web českého hokeje",
        "href": "https://www.hokej.cz/klub/hc-verva-litvinov/823",
        "real_result": true
      }
    ],
    "user": "anon_ratio_low",
    "timestamp": "2024-04-03T07:29:20.633Z"
  },
  {
    "query": "kam na turistiku v alpách",
    "language": "queries",
    "results": [
      {
        "title": "Alpy 2024 - zájezdy CK Alpina - Hory, turistika, cyklo, MTB",
        "href": "https://www.alpina.cz/alpy/",
        "real_result": true
      },
      {
        "title": "Pěší turistika a horské výstupy v Jižním Tyrolsku | Nejlepší…",
        "href": "https://www.suedtirol.info/cs/cz/zazitky-a-akce/sportovni-aktivity/pesi-turistika-a-horske-vystupy",
        "real_result": true
      },
      {
        "title": "Tipy na výlety a túry v Alpách | Natreku.cz",
        "href": "https://www.natreku.cz/turistika-treking-alpy/",
        "real_result": true
      },
      {
        "title": "Tipy pro pěší turisty",
        "href": "https://www.austria.info/cz/aktivity-a-zazitky/turistika-a-alpy/nejlepsi-tipy-na-turistiku-v-rakousku",
        "real_result": true
      },
      {
        "title": "Rakouské Alpy v létě - 11 tipů, kam vyrazit? | Kdy a kam na…",
        "href": "https://www.kdyjet.cz/rakouske-alpy-v-lete/",
        "real_result": true
      },
      {
        "title": "S průvodcem i na vlastní pěst: turistika na sněžnicích v…",
        "href": "https://www.gastein.com/cz/zkusenosti/sport-a-priroda/vylet-na-sneznicich/",
        "real_result": true
      },
      {
        "title": "Rakousko - horská turistika",
        "href": "https://www.alpina.cz/rakousko/turistika/",
        "real_result": true
      },
      {
        "title": "Známe jedny z nejhezčích túr v Alpách. Tipy na prodloužený víkend",
        "href": "https://www.idnes.cz/cestovani/kolem-sveta/prodlouzeny-vikend-v-alpach-tipy.A151013_143257_kolem-sveta_tom",
        "real_result": true
      },
      {
        "title": "Turistické zájezdy | CK Víkend",
        "href": "https://www.ck-vikend.cz/index-turisticky-poznavaci-zajezd.php?AKCE=zajezdy&KOD=turistika-alpy-dolomity",
        "real_result": true
      },
      {
        "title": "Hike World I Pěší turistika v oblasti Nassfeld-Pressegger See",
        "href": "https://www.nassfeld.at/cz/Summer-World/Hike-World",
        "real_result": true
      },
      {
        "title": "Bavorské Alpy – nejlepší horské treky, túry a feraty…",
        "href": "https://www.svetoutdooru.cz/bavorske-alpy-nejlepsi-horske-treky-tury-a-feraty/",
        "real_result": true
      },
      {
        "title": "Naučné stezky a trasy - Tipy na výlety po Česku",
        "href": "https://www.kudyznudy.cz/co-chcete-delat/priroda/naucne-stezky-a-trasy",
        "real_result": true
      }
    ],
    "user": "anon_ratio_low",
    "timestamp": "2024-04-03T07:45:54.540Z"
  },
  {
    "query": "sport.cz",
    "language": "queries",
    "results": [
      {
        "title": "Sport.cz - s námi jste ve hře",
        "href": "https://www.sport.cz/",
        "real_result": true
      },
      {
        "title": "Sport.cz - Vše o sportu online < Internetové vyhledávače",
        "href": "https://ivyhledavace.cz/sport-cz/",
        "real_result": true
      },
      {
        "title": "Sport.cz - Česká Wikipedie",
        "href": "https://www.czech.wiki/wiki/Sport.cz",
        "real_result": true
      },
      {
        "title": "Videa›Sport.cz",
        "href": "//search.seznam.cz/videa/?q=sport.cz#utm_content=organic&utm_term=sport.cz&utm_medium=hint&utm_source=search.seznam.cz",
        "real_result": false
      },
      {
        "title": "Sport.cz - Právě dnes",
        "href": "https://pravednes.cz/nmoto.source",
        "real_result": true
      },
      {
        "title": "Sportovní novinky – program, tabulky, kurzy, sázky, výsledky",
        "href": "https://www.sazkove-kancelare.com/sport/",
        "real_result": true
      },
      {
        "title": "Sportovní oblečení, vybavení, náčiní a fitness výživové doplňky…",
        "href": "https://www.live4sport.cz/",
        "real_result": true
      },
      {
        "title": "Archiv online reportáží - Sport.cz",
        "href": "https://online.sport.cz/",
        "real_result": true
      },
      {
        "title": "A3 Sport | A3 Sport – Prodej sportovní obuvi a oblečení",
        "href": "https://www.a3sport.cz/",
        "real_result": true
      },
      {
        "title": "Sport.cz – Aplikace na Google Play",
        "href": "https://play.google.com/store/apps/details?id=cz.seznam.sport&hl=cs",
        "real_result": true
      },
      {
        "title": "Sport.cz | Stream",
        "href": "https://www.stream.cz/sluzba/sport",
        "real_result": true
      }
    ],
    "user": "anon_ratio_low",
    "timestamp": "2024-04-03T08:02:25.941Z"
  },
  {
    "query": "sport idnes",
    "language": "queries",
    "results": [
      {
        "title": "Sport Idnes.cz – Nejlepší sport",
        "href": "https://www.idnes.cz/sport",
        "real_result": true
      },
      {
        "title": "Idnes.cz – s námi víte víc",
        "href": "https://www.idnes.cz/",
        "real_result": true
      },
      {
        "title": "Sportovní výsledky - Sport - Idnes.cz",
        "href": "https://www.idnes.cz/sport/sportovni-vysledky",
        "real_result": true
      },
      {
        "title": "Sportovní výsledky - Sport - Idnes.cz",
        "href": "https://www.idnes.cz/sport/sportovni-vysledky?date=18.10.2023&filter=future",
        "real_result": true
      },
      {
        "title": "Sportovní výsledky - Sport - Idnes.cz",
        "href": "https://www.idnes.cz/sport/sportovni-vysledky?date=5.3.2024",
        "real_result": true
      }
    ],
    "user": "anon_ratio_low",
    "timestamp": "2024-04-03T08:18:57.160Z"
  },
  {
    "query": "AMD ryzen 7",
    "language": "queries",
    "results": [
      {
        "title": "Nabídky ze Zboží.cz",
        "href": "https://www.zbozi.cz/nabidka/ca010000676032cc76436620ff4aa2e605356772/",
        "real_result": false
      },
      {
        "title": "Procesory AMD Ryzen 7 - Alza dny jsou tady",
        "href": "https://www.alza.cz/amd-ryzen-7/18869776.htm",
        "real_result": true
      },
      {
        "title": "AMD Ryzen 7 - 11 produktů na Zboží.cz",
        "href": "https://www.zbozi.cz/pocitace/pocitacove-komponenty/procesory/",
        "real_result": true
      },
      {
        "title": "AMD Ryzen 5 5600G | AMD",
        "href": "https://www.amd.com/en/products/apu/amd-ryzen-5-5600g",
        "real_result": true
      },
      {
        "title": "Zboží.cz›AMD ryzen 7",
        "href": "https://www.zbozi.cz/hledej/?q=amd%20ryzen%207#utm_source=search.seznam.cz&utm_medium=hint&utm_content=products-opesBB&utm_ab=3069%2F5650&utm_term=AMD%20ryzen%207&utm_query=amd%20ryzen%207",
        "real_result": false
      },
      {
        "title": "AMD Ryzen 7 je tu, máme dotestováno. Budete mít radost…",
        "href": "https://pctuning.cz/article/amd-ryzen-7-je-tu-mame-dotestovano-budete-mit-radost",
        "real_result": true
      },
      {
        "title": "AMD Ryzen 7 2700X: Zen vyšponován na maximum | PCTuning.cz",
        "href": "https://pctuning.cz/article/amd-ryzen-7-2700x-zen-vysponovan-na-maximum",
        "real_result": true
      },
      {
        "title": "AMD Ryzen 7 5700G (100-100000263BOX) | Tsbohemia.CZ",
        "href": "https://www.tsbohemia.cz/amd-ryzen-7-5700g_d384165.html",
        "real_result": true
      },
      {
        "title": "Procesory AMD Ryzen 7 | Alza.cz",
        "href": "https://www.alza.cz/amd-ryzen-7/18869776.htm",
        "real_result": true
      },
      {
        "title": "Výkonný a pořád levný: AMD Ryzen 7 2700X v testu",
        "href": "https://www.chip.cz/vykonny-porad-levny-amd-ryzen-7-2700x-v-testu",
        "real_result": true
      },
      {
        "title": "Ryzen C7: hodlá AMD uspět tam, kde Intel pohořel? | Svět…",
        "href": "https://www.svetandroida.cz/amd-ryzen-7c-mobile/",
        "real_result": true
      },
      {
        "title": "AMD Ryzen 7 1800X v testech | Alza.cz",
        "href": "https://www.alza.cz/vse-o-procesorech-amd-zen",
        "real_result": true
      },
      {
        "title": "Procesory AMD Ryzen 7 - Zbozi.cz",
        "href": "https://www.zbozi.cz/pocitace/pocitacove-komponenty/procesory/?vyrobce=amd_ryzen-7",
        "real_result": true
      },
      {
        "title": "Příplatek nedává smysl. Test procesoru AMD Ryzen 7 7700X",
        "href": "https://www.zive.cz/clanky/priplatek-nedava-smysl-test-procesoru-amd-ryzen-7-7700x/sc-3-a-224333/default.aspx",
        "real_result": true
      },
      {
        "title": "Nabídky ze Zboží.cz",
        "href": "https://www.zbozi.cz/nabidka/a9000000eb909f63829c5444e9064eec019b219f/",
        "real_result": false
      }
    ],
    "user": "anon_ratio_low",
    "timestamp": "2024-04-03T08:35:24.973Z"
  },
  {
    "query": "HC Olomouc",
    "language": "queries",
    "results": [
      {
        "title": "HC Olomouc",
        "href": "/obrazky/?q=HC+Olomouc#utm_content=teamLeft&utm_term=HC Olomouc&utm_medium=hint&utm_source=search.seznam.cz",
        "real_result": false
      },
      {
        "title": "Oficiální webové stránky týmu HC Olomouc",
        "href": "https://www.hc-olomouc.cz/",
        "real_result": true
      },
      {
        "title": "HC Olomouc s.r.o. - Zimní stadion Olomouc - Olomouc | ekatalog…",
        "href": "https://www.ekatalog.cz/firma/309439-hc-olomouc-sro-zimni-stadion-olomouc/",
        "real_result": true
      },
      {
        "title": "HC Olomouc – Wikipedie",
        "href": "https://cs.wikipedia.org/wiki/HC_Olomouc",
        "real_result": true
      },
      {
        "title": "Obrázky›HC Olomouc",
        "href": "/obrazky/?q=HC+Olomouc&fulltext=&sourceid=fulltext&thru=hint-obrazky-carousel#utm_content=carousel&utm_term=HC%20Olomouc&utm_medium=hint&utm_source=search.seznam.cz",
        "real_result": false
      },
      {
        "title": "HC Olomouc s.r.o. - Olomouc - rejstřík firem ifirmy.cz",
        "href": "https://ifirmy.cz/firma/166325-hc-olomouc-sro",
        "real_result": true
      },
      {
        "title": "HC Olomouc - Olomouc.CZ",
        "href": "https://www.olomouc.cz/firmy/HC-Olomouc-id1900",
        "real_result": true
      },
      {
        "title": "HC Olomouc o.s., Olomouc - Nová Ulice - ZlatéStránky.cz",
        "href": "https://www.zlatestranky.cz/profil/H1026171",
        "real_result": true
      },
      {
        "title": "HC Olomouc, s.r.o. (Olomouc, Nová Ulice) • Firmy.cz",
        "href": "https://www.firmy.cz/detail/736139-hc-olomouc-olomouc-nova-ulice.html",
        "real_result": true
      },
      {
        "title": "Tipsport extraliga 2023/2024 | HC Olomouc",
        "href": "https://www.hc-olomouc.cz/matches/MUZ",
        "real_result": true
      },
      {
        "title": "Informace o stadionu | HC Olomouc",
        "href": "https://www.hc-olomouc.cz/informace-o-stadionu",
        "real_result": true
      },
      {
        "title": "Zimní stadion Olomouc – Wikipedie",
        "href": "https://cs.wikipedia.org/wiki/Zimn%C3%AD_stadion_Olomouc",
        "real_result": true
      }
    ],
    "user": "anon_ratio_low",
    "timestamp": "2024-04-03T08:52:08.099Z"
  },
  {
    "query": "virtuální realita",
    "language": "queries",
    "results": [
      {
        "title": "Virtuální realita - Alza dny jsou tady",
        "href": "https://www.alza.cz/gaming/virtualni-realita/18856436.htm",
        "real_result": true
      },
      {
        "title": "Půjčte si virtuální realitu - VR set + 25 top her k tomu",
        "href": "https://www.adrop.cz/vr",
        "real_result": true
      },
      {
        "title": "Virtuální realita - Svět atrakcí na jednom místě",
        "href": "http://funnytony.cz/nabidka-atrakce-vrealita",
        "real_result": true
      },
      {
        "title": "Virtuální realita: až - 50 % - Vybírejte ze široké nabídky",
        "href": "https://skrz.cz/virtualni-realita",
        "real_result": true
      },
      {
        "title": "Zboží.cz›Virtuální realita",
        "href": "https://www.zbozi.cz/elektronika/herni-zarizeni/virtualni-realita/#utm_source=search.seznam.cz&utm_medium=hint&utm_content=cards-category_opesBB&utm_idzbozientity=5852&utm_ab=3069%2F5650&utm_term=virtu%C3%A1ln%C3%AD%20realita&utm_query=virtu%C3%A1ln%C3%AD%20realita",
        "real_result": false
      },
      {
        "title": "Virtuální realita – Wikipedie",
        "href": "https://cs.wikipedia.org/wiki/Virtu%C3%A1ln%C3%AD_realita",
        "real_result": true
      },
      {
        "title": "Virtuální realita - Zábava na svatbu - DJs-nasvatbu.cz",
        "href": "https://zabava-nasvatbu.cz/ostatni_sluzby/virtualni-realita/",
        "real_result": true
      },
      {
        "title": "Videa›Virtuální realita",
        "href": "//search.seznam.cz/videa/?q=virtu%C3%A1ln%C3%AD+realita#utm_content=organic&utm_term=virtu%C3%A1ln%C3%AD%20realita&utm_medium=hint&utm_source=search.seznam.cz",
        "real_result": false
      },
      {
        "title": "Virtuální realita - wiki34.com",
        "href": "https://cs.wiki34.com/wiki/Realidad_Virtual",
        "real_result": true
      },
      {
        "title": "Virtuální realita | Alza.cz",
        "href": "https://www.alza.cz/gaming/virtualni-realita/18856436.htm",
        "real_result": true
      },
      {
        "title": "Virtuální realita – Multimediaexpo.cz",
        "href": "http://www.multimediaexpo.cz/mmecz/index.php/Virtu%C3%A1ln%C3%AD_realita",
        "real_result": true
      },
      {
        "title": "Co je to virtuální realita | Technologický slovník pojmů",
        "href": "https://blog.cinkly.cz/slovnik-pojmu/virtualni-realit",
        "real_result": true
      },
      {
        "title": "Jak funguje virtuální realita | Tasty Air",
        "href": "https://www.tastyair.cz/blog/jak-funguje-virtualni-realita/",
        "real_result": true
      },
      {
        "title": "Rozšířená a virtuální realita | Datart",
        "href": "https://www.datart.cz/novinky/technologie/rozsirena-a-virtualni-realita",
        "real_result": true
      },
      {
        "title": "Virtuální realita | Electroworld.cz",
        "href": "https://www.electroworld.cz/virtualni-realita",
        "real_result": true
      },
      {
        "title": "Co je to virtuální realita | Alza.cz",
        "href": "https://www.alza.cz/virtualni-realita",
        "real_result": true
      },
      {
        "title": "Virtuální realita - Na Zboží.cz již od 299 Kč",
        "href": "https://www.zbozi.cz/elektronika/herni-zarizeni/virtualni-realita/",
        "real_result": true
      },
      {
        "title": "Virtuální realita - Virze - Největší VR aréna v Plzni",
        "href": "https://virze.cz/",
        "real_result": true
      },
      {
        "title": "Virtuální realita - CZC.cz - dvojky hrají fér",
        "href": "https://www.czc.cz/virtualni-realita/produkty",
        "real_result": true
      },
      {
        "title": "Nabídky ze Zboží.cz",
        "href": "https://www.zbozi.cz/nabidka/4c5200007324c58ff7b3d99c030e2ecbd75e9f7c/",
        "real_result": false
      }
    ],
    "user": "anon_ratio_low",
    "timestamp": "2024-04-03T09:08:42.098Z"
  },
  {
    "query": "sport O2 TV",
    "language": "queries",
    "results": [
      {
        "title": "Live Sport Přenosy - Sledujte na TV Tipsport",
        "href": "https://www.tipsport.cz/PartnerRedirectAction.do",
        "real_result": true
      },
      {
        "title": "O2 TV Sport | O2 TV Sport",
        "href": "https://www.o2tvsport.cz/",
        "real_result": true
      },
      {
        "title": "O2 TV 2.0",
        "href": "https://www.o2tv.cz/",
        "real_result": true
      },
      {
        "title": "O2 | Nejlepší sport živě v O2 TV | Sportovní přenosy přes…",
        "href": "https://www.o2.cz/osobni/televize/sport",
        "real_result": true
      },
      {
        "title": "O2 TV Sport - YouTube",
        "href": "https://www.youtube.com/channel/UCkXKF40E3cvGxoXzpmmp9UQ",
        "real_result": true
      },
      {
        "title": "O2 | Sledujte špičkové MMA živě | O2 TV",
        "href": "https://www.o2.cz/osobni/televize/sport-mma",
        "real_result": true
      },
      {
        "title": "Videa›Sport O2 TV",
        "href": "//search.seznam.cz/videa/?q=sport+O2+TV#utm_content=organic&utm_term=sport%20O2%20TV&utm_medium=hint&utm_source=search.seznam.cz",
        "real_result": false
      },
      {
        "title": "O2 TV Sport -  Sledujte náš nový web o2tvsport.cz!..",
        "href": "https://www.facebook.com/O2SportCZ/posts/-sledujte-n%C3%A1%C5%A1-nov%C3%BD-web-o2tvsportcz-dozv%C3%ADte-se-co-by-v%C3%A1m-v-o2-tv-nem%C4%9Blo-uniknout-/3300123266881110/",
        "real_result": true
      },
      {
        "title": "O2 TV Sport - Demisport",
        "href": "https://www.demisport.cz/o2-tv-sport/",
        "real_result": true
      },
      {
        "title": "Konec vysílání O2 TV Tenis, start Premier Sport 3 - YouTube",
        "href": "https://www.youtube.com/watch?v=wU9yrMTGnzg",
        "real_result": true
      },
      {
        "title": "Diskuze - O2 TV rozšiřuje sportovní obsah o kanály Nova Sport 5…",
        "href": "https://www.sport.cz/diskuze/moto-formule-1-o2-tv-rozsiruje-sportovni-obsah-o-kanaly-nova-sport-5-a-nova-sport-6-divaci-se-mohou-tesit-na-prenosy-z-f1-5021344",
        "real_result": true
      },
      {
        "title": "O2 TV Sport | O2 TV Sport",
        "href": "https://www.o2sport.cz/",
        "real_result": true
      }
    ],
    "user": "anon_ratio_low",
    "timestamp": "2024-04-03T09:25:26.906Z"
  },
  {
    "query": "Trolltunga túra",
    "language": "queries",
    "results": [
      {
        "title": "Trolltunga - Vše co potřebujete vědět před túrou na Trolí jazyk",
        "href": "https://realcamplife.com/trolltunga-prakticke-informace/",
        "real_result": true
      },
      {
        "title": "Obrázky›Trolltunga túra",
        "href": "/obrazky/?q=Trolltunga+t%C3%BAra&fulltext=&sourceid=fulltext&thru=hint-obrazky-super#utm_content=super&utm_term=Trolltunga%20t%C3%BAra&utm_medium=hint&utm_source=search.seznam.cz",
        "real_result": false
      },
      {
        "title": "Cestopis Norsko 2017 - Odda, Trolltunga - Cesta na trolí jazyk…",
        "href": "https://www.gigaplaces.com/clanek-cestopis-norsko-2017-odda-trolltunga/",
        "real_result": true
      },
      {
        "title": "Trolltunga – Wikipedie",
        "href": "https://cs.wikipedia.org/wiki/Trolltunga#:~:text=Trolltunga%20(Trol%C3%AD%20jazyk)%20je%20skaln%C3%AD,Aby%20nebyl%20poru%C5%A1en%20p%C5%99%C3%ADrodn%C3%AD%20vzhled",
        "real_result": true
      },
      {
        "title": "Trolltunga alias Trolí jazyk | Dovolená Norsko 2024 - CK…",
        "href": "https://www.dovolenanorsko.cz/clanky/trolltunga-clanek/",
        "real_result": true
      },
      {
        "title": "Výstup na útes Trolltunga v Norsku, tuhle fotku prostě musíte…",
        "href": "https://www.svetoutdooru.cz/hory/vystup-na-utes-trolltunga-v-norsku-tuhle-fotku-proste-musite-mit/",
        "real_result": true
      },
      {
        "title": "Trolltunga, Norsko - TRVL.cz",
        "href": "https://trvl.cz/misto/trolltunga/",
        "real_result": true
      },
      {
        "title": "Trolltunga – jazyk vyplazený 1100 metrů nad mořem | Cestovatelé…",
        "href": "https://www.cestovatele.info/clanky/trolltunga-jazyk-vyplazeny-1100-metru-nad-morem/",
        "real_result": true
      },
      {
        "title": "Trolí jazyk, šílená vyhlídka z útesu v 700 m v Norsku. Troufáte si?",
        "href": "https://www.idnes.cz/cestovani/kolem-sveta/vyhlidka-trolltunga-neboli-troli-jazyk-v-norsku.A120922_135849_kolem-sveta_tom",
        "real_result": true
      },
      {
        "title": "Norská vyhlídka Trolltunga učarovala světu. Jak se vyhnout…",
        "href": "https://radiozurnal.rozhlas.cz/norska-vyhlidka-trolltunga-ucarovala-svetu-jak-se-vyhnout-fronte-na-vyhlasenou-7277927",
        "real_result": true
      },
      {
        "title": "Fotka na Trolím jazyku je hit. Stojí se na ni hodinové fronty",
        "href": "https://www.novinky.cz/clanek/cestovani-fotka-na-trolim-jazyku-je-hit-stoji-se-na-ni-hodinove-fronty-40050908",
        "real_result": true
      }
    ],
    "user": "anon_ratio_low",
    "timestamp": "2024-04-03T09:42:00.808Z"
  },
  {
    "query": "david pastrňák",
    "language": "queries",
    "results": [
      {
        "title": "David Pastrňák produkty - Největší fanshop NHL",
        "href": "https://www.fanda-nhl.cz/produkty-nhl/",
        "real_result": true
      },
      {
        "title": "David Pastrňák – Wikipedie",
        "href": "https://cs.wikipedia.org/wiki/David_Pastr%C5%88%C3%A1k",
        "real_result": true
      },
      {
        "title": "David Pastrňák - dasbestelexikon.de",
        "href": "https://www.dasbestelexikon.de/cs/wiki/David_Pastr%c5%88%c3%a1k",
        "real_result": true
      },
      {
        "title": "David Pastrňák - Czech-profile.cz",
        "href": "https://www.czech-profile.cz/david-pastrnak/",
        "real_result": true
      },
      {
        "title": "Pastrňák a Zacha stvrdili svými góly v NHL výhru Bostonu",
        "href": "https://www.ceskenoviny.cz/zpravy/2500459",
        "real_result": true
      },
      {
        "title": "David Pastrňák | Celebrity Blesk.cz",
        "href": "https://celebwiki.blesk.cz/osobnost/3545/david-pastrnak/",
        "real_result": true
      },
      {
        "title": "David Pastrňák - Životopis | Osobnosti.CZ",
        "href": "https://zivotopis.osobnosti.cz/david-pastrnak.php",
        "real_result": true
      },
      {
        "title": "David Pastrňák | vipstar.cz",
        "href": "https://vipstar.cz/stitek/david-pastrnak/",
        "real_result": true
      },
      {
        "title": "Pastrňák se Zachou rozhodli, Mrázek a Vejmelka vychytali výhru",
        "href": "https://www.ceskenoviny.cz/zpravy/2498075",
        "real_result": true
      },
      {
        "title": "David Pastrňák. Skromná hyperaktivní hvězda, která má vztah k Havířovu i Karviné",
        "href": "https://karvinsky.denik.cz/zpravy_region/david-patrnak-nova-smlouva-nhl.html",
        "real_result": true
      },
      {
        "title": "David Pastrňák | Osobnosti.CZ",
        "href": "https://www.osobnosti.cz/david-pastrnak.php",
        "real_result": true
      }
    ],
    "user": "anon_ratio_low",
    "timestamp": "2024-04-03T09:58:32.269Z"
  },
  {
    "query": "student agency",
    "language": "queries",
    "results": [
      {
        "title": "Akční letenky - STUDENT AGENCY",
        "href": "https://www.studentagency.cz/letenky/",
        "real_result": true
      },
      {
        "title": "| Student Agency | Vydejte se za zážitky se Student Agency.",
        "href": "https://www.studentagency.cz/",
        "real_result": true
      },
      {
        "title": "| Student Agency | Student Agency",
        "href": "https://www.studentagency.eu/en",
        "real_result": true
      },
      {
        "title": "Student Agency | Morava - katalog firem",
        "href": "http://www.morava-katalog.cz/firma/30640/student-agency-sro.html",
        "real_result": true
      },
      {
        "title": "Student Agency | Brno - katalog firem",
        "href": "http://www.brno-katalog.cz/firma/30640/student-agency-sro.html",
        "real_result": true
      },
      {
        "title": "Student Agency | Zlín - katalog firem",
        "href": "http://www.zlin-katalog.cz/firma/30640/student-agency-sro.html",
        "real_result": true
      },
      {
        "title": "Student Agency | Chomutov - katalog firem",
        "href": "http://www.chomutov-katalog.cz/firma/30640/student-agency-sro.html",
        "real_result": true
      },
      {
        "title": "Student Agency – Wikipedie",
        "href": "https://cs.wikipedia.org/wiki/Student_Agency",
        "real_result": true
      },
      {
        "title": "Student Agency - dasbestelexikon.de",
        "href": "https://www.dasbestelexikon.de/cs/wiki/Student_Agency",
        "real_result": true
      },
      {
        "title": "| Student Agency | Kontakty",
        "href": "https://www.studentagency.cz/kontakty/",
        "real_result": true
      },
      {
        "title": "| Student Agency | O nás",
        "href": "https://www.studentagency.cz/o-nas/profil-spolecnosti/",
        "real_result": true
      }
    ],
    "user": "anon_ratio_low",
    "timestamp": "2024-04-03T10:15:03.858Z"
  },
  {
    "query": "Intel i7",
    "language": "queries",
    "results": [
      {
        "title": "Nabídky ze Zboží.cz",
        "href": "https://www.zbozi.cz/nabidka/7844000055fd6f3c5032bd23afdfb50445e9e361/",
        "real_result": false
      },
      {
        "title": "Procesory Intel Core i7 - Alza dny jsou tady",
        "href": "https://www.alza.cz/intel-core-i7/18869765.htm",
        "real_result": true
      },
      {
        "title": "Zboží.cz›Intel i7",
        "href": "https://www.zbozi.cz/hledej/?q=intel%20i7#utm_source=search.seznam.cz&utm_medium=hint&utm_content=products-opesBB&utm_ab=3069%2F5650&utm_term=Intel%20i7&utm_query=intel%20i7",
        "real_result": false
      },
      {
        "title": "Procesory Intel Core i7 - Zbozi.cz",
        "href": "https://www.zbozi.cz/pocitace/pocitacove-komponenty/procesory/?vyrobce=intel_core-i7",
        "real_result": true
      },
      {
        "title": "Procesory Intel Core i7 | Alza.cz",
        "href": "https://www.alza.cz/intel-core-i7/18869765.htm",
        "real_result": true
      },
      {
        "title": "Obrázky›Intel i7",
        "href": "/obrazky/?q=Intel+i7&fulltext=&sourceid=fulltext&thru=hint-obrazky-carousel#utm_content=carousel&utm_term=Intel%20i7&utm_medium=hint&utm_source=search.seznam.cz",
        "real_result": false
      },
      {
        "title": "intel core i7 procesory – Heureka.cz",
        "href": "https://www.heureka.cz/?h%5Bfraze%5D=intel+core+i7+procesory",
        "real_result": true
      },
      {
        "title": "Procesory Intel Core i7, 8 jader – Heureka.cz",
        "href": "https://procesory.heureka.cz/f:2799:105502;4846:42746709/",
        "real_result": true
      },
      {
        "title": "Test Intel Core i7-6700K, i7-8700K a AMD Ryzen 7 1700X…",
        "href": "https://pctuning.cz/article/test-intel-core-i7-6700k-i7-8700k-a-amd-ryzen-7-1700x",
        "real_result": true
      },
      {
        "title": "Osobní počítače Intel Core i7 | CZC.cz",
        "href": "https://www.czc.cz/pocitace/produkty?typ-procesoru=intel-core-i7_3",
        "real_result": true
      },
      {
        "title": "PC s procesorem Intel Core i7 | Datart",
        "href": "https://www.datart.cz/pocitace-s-procesorem-intel-core-i7.html",
        "real_result": true
      },
      {
        "title": "Core i7 - LGA 1200 - Intel - Procesory - Komponenty | Mironet…",
        "href": "https://www.mironet.cz/procesory/intel/lga-1200/core-i7+c35945/",
        "real_result": true
      },
      {
        "title": "Intel Core i7-12700 (BX8071512700) procesor | Electroworld.cz",
        "href": "https://www.electroworld.cz/intel-core-i7-12700",
        "real_result": true
      },
      {
        "title": "Porovnání aktuálních možností vě výběru procesoru — Cegra",
        "href": "https://www.cegra.cz/porovnani-aktualnich-moznosti-ve-vyberu-procesoru/",
        "real_result": true
      },
      {
        "title": "Nabídky ze Zboží.cz",
        "href": "https://www.zbozi.cz/nabidka/35340200e1174927ffad5f33c7619a5e1270eac2/",
        "real_result": false
      }
    ],
    "user": "anon_ratio_low",
    "timestamp": "2024-04-03T10:31:35.017Z"
  },
  {
    "query": "isport.cz",
    "language": "queries",
    "results": [
      {
        "title": "iSport.cz - Sportovní zprávy, výsledky, reportáže",
        "href": "https://isport.blesk.cz/",
        "real_result": true
      },
      {
        "title": "iSport LIFE | iSportLIFE | iSport.cz",
        "href": "https://isport.blesk.cz/isportlife",
        "real_result": true
      },
      {
        "title": "iSport.cz - Sportovní zprávy, výsledky, reportáže",
        "href": "https://isport.blesk.cz/?page=2",
        "real_result": true
      },
      {
        "title": "Rezervační systém iSport pro sporty a cvičení",
        "href": "https://www.isportsystem.cz/",
        "real_result": true
      },
      {
        "title": "iSport.cz - Právě dnes",
        "href": "https://pravednes.cz/deniksport.source",
        "real_result": true
      },
      {
        "title": "Redakce iSport.cz: Kdo je kdo? Kontakty a tiráž",
        "href": "https://isport.blesk.cz/clanek/titulni-strana/391036/redakce-isport-cz-kdo-je-kdo-kontakty-a-tiraz.html",
        "real_result": true
      },
      {
        "title": "iSport.cz - Práve dnes",
        "href": "https://pravednes.sk/deniksport.source",
        "real_result": true
      },
      {
        "title": "Live stream | Tv.iSport.cz",
        "href": "https://tv.isport.blesk.cz/live",
        "real_result": true
      },
      {
        "title": "iSport.cz - Sportovní zprávy, výsledky, reportáže",
        "href": "https://isport.blesk.cz/?season=4029&page=6",
        "real_result": true
      },
      {
        "title": "iSport TV | Tv.iSport.cz",
        "href": "https://tv.isport.blesk.cz/",
        "real_result": true
      }
    ],
    "user": "anon_ratio_low",
    "timestamp": "2024-04-03T10:48:11.705Z"
  },
  {
    "query": "pelikan letenky",
    "language": "queries",
    "results": [
      {
        "title": "Levné letenky Pelikan.cz - Nakupujte již od 490 Kč",
        "href": "https://www.pelikan.cz/cs",
        "real_result": true
      },
      {
        "title": "Letuška - Jednička na letenky - Rezervujte si letenky včas",
        "href": "https://www.letuska.cz/",
        "real_result": true
      },
      {
        "title": "Nejlevnější letenky do celého světa | Pelikan.cz",
        "href": "https://www.pelikan.cz/cs",
        "real_result": true
      },
      {
        "title": "Levné letenky | Pelikan.cz",
        "href": "https://www.pelikan.cz/levne-letenky/",
        "real_result": true
      },
      {
        "title": "Oficiální stránka Pelikan.cz",
        "href": "https://cestovani.pelikan.cz/",
        "real_result": true
      },
      {
        "title": "Pelikán letenky - levné letenky last minute od Pelikán.cz",
        "href": "http://www.letenky-levne-online.cz/pelikan-letenky/",
        "real_result": true
      },
      {
        "title": "Letenky Pelikán (Jihlava) • Firmy.cz",
        "href": "https://www.firmy.cz/detail/2628987-letenky-pelikan-jihlava.html",
        "real_result": true
      },
      {
        "title": "Letenky Pelikán",
        "href": "https://www.firmablizko.cz/303219-letenky-pelikan",
        "real_result": true
      },
      {
        "title": "Pelikán.cz - nejvýhodnější letenky 10 % zpět | Tipli",
        "href": "https://www.tipli.cz/obchod/pelikan-cz",
        "real_result": true
      },
      {
        "title": "Pelikán letenky → Akční ceny online (až -80 %)",
        "href": "https://www.letenkyzababku.eu/pelikan-letenky/",
        "real_result": true
      },
      {
        "title": "Pelikan letenky - akční letenky do celého světa",
        "href": "https://www.cestujsnadno.cz/pelikan-letenky/page/2/",
        "real_result": true
      },
      {
        "title": "Pelikán letenky - návod jak nakoupit levné letenky - Honzovy…",
        "href": "https://honzovyletenky.cz/pelikan-letenky/",
        "real_result": true
      },
      {
        "title": "Letenky levně - zajezdy.name",
        "href": "http://www.zajezdy.name/zajezdy-letenky-levne-ubytovani.html",
        "real_result": true
      },
      {
        "title": "Avia-Scanner - Srovnání levných letenek",
        "href": "http://cz.avia-scanner.com/",
        "real_result": true
      }
    ],
    "user": "anon_ratio_low",
    "timestamp": "2024-04-03T11:04:44.837Z"
  },
  {
    "query": "HC Sparta Praha",
    "language": "queries",
    "results": [
      {
        "title": "Oficiální e-shop HC Sparta - Dresy, šály, oblečení a další",
        "href": "https://fanshop.hcsparta.cz/",
        "real_result": true
      },
      {
        "title": "HC Sparta Praha",
        "href": "/obrazky/?q=HC+Sparta+Praha#utm_content=teamLeft&utm_term=HC Sparta Praha&utm_medium=hint&utm_source=search.seznam.cz",
        "real_result": false
      },
      {
        "title": "HC Sparta Praha » Oficiální internetové stránky",
        "href": "https://www.hcsparta.cz/index.asp",
        "real_result": true
      },
      {
        "title": "HC Sparta Praha",
        "href": "https://www.hcsparta.cz/membership.asp",
        "real_result": true
      },
      {
        "title": "Hokejisté Sparty zdolali na úvod semifinále mistrovský Třinec 3:0",
        "href": "https://www.ceskenoviny.cz/zpravy/2499759",
        "real_result": true
      },
      {
        "title": "HC Sparta Praha – Wikipedie",
        "href": "https://cs.wikipedia.org/wiki/HC_Sparta_Praha",
        "real_result": true
      },
      {
        "title": "Semifinále hokejové extraligy začne v neděli v Pardubicích",
        "href": "https://www.ceskenoviny.cz/zpravy/2498840",
        "real_result": true
      },
      {
        "title": "HC Sparta Praha a.s. | Česko-Katalog.cz",
        "href": "http://www.cesko-katalog.cz/firma/200156/hc-sparta-praha-as.html",
        "real_result": true
      },
      {
        "title": "AC Sparta Praha – Wikipedie",
        "href": "https://cs.wikipedia.org/wiki/AC_Sparta_Praha",
        "real_result": true
      },
      {
        "title": "Obrázky›HC Sparta Praha",
        "href": "/obrazky/?q=HC+Sparta+Praha&fulltext=&sourceid=fulltext&thru=hint-obrazky-carousel#utm_content=carousel&utm_term=HC%20Sparta%20Praha&utm_medium=hint&utm_source=search.seznam.cz",
        "real_result": false
      },
      {
        "title": "Hokejisté Sparty počtvrté udolali Liberec a jsou v semifinále extraligy",
        "href": "https://prazska.drbna.cz/sport/hokej/14277-hokejiste-sparty-poctvrte-udolali-liberec-a-jsou-v-semifinale-extraligy.html",
        "real_result": true
      },
      {
        "title": "Sparta (hokejový klub) - wiki7.org",
        "href": "https://cs.wiki7.org/wiki/%D0%A1%D0%BF%D0%B0%D1%80%D1%82%D0%B0_(%D1%85%D0%BE%D0%BA%D0%BA%D0%B5%D0%B9%D0%BD%D1%8B%D0%B9_%D0%BA%D0%BB%D1%83%D0%B1)",
        "real_result": true
      },
      {
        "title": "HC Sparta Praha a.s. | Morava - katalog firem",
        "href": "http://www.morava-katalog.cz/firma/200156/hc-sparta-praha-as.html",
        "real_result": true
      }
    ],
    "user": "anon_ratio_low",
    "timestamp": "2024-04-03T11:21:23.537Z"
  },
  {
    "query": "HC Energie Karlovy Vary",
    "language": "queries",
    "results": [
      {
        "title": "HC Energie Karlovy Vary",
        "href": "/obrazky/?q=HC+Energie+Karlovy+Vary#utm_content=teamLeft&utm_term=HC Energie Karlovy Vary&utm_medium=hint&utm_source=search.seznam.cz",
        "real_result": false
      },
      {
        "title": "HC Energie Karlovy Vary",
        "href": "https://hokejkv.cz/",
        "real_result": true
      },
      {
        "title": "HC Energie Karlovy Vary – Wikipedie",
        "href": "https://cs.wikipedia.org/wiki/HC_Energie_Karlovy_Vary",
        "real_result": true
      },
      {
        "title": "HC Energie Karlovy Vary s.r.o. - Karlovy Vary | netkatalog.cz",
        "href": "https://www.netkatalog.cz/firma/355271-hc-energie-karlovy-vary-sro/",
        "real_result": true
      },
      {
        "title": "Hokejové Karlovy Vary mají nové trenéry. Povedou je legendy z Nagana",
        "href": "https://tn.nova.cz/sport/clanek/548256-hokejove-karlovy-vary-maji-nove-trenery-povedou-je-legendy-z-nagana",
        "real_result": true
      },
      {
        "title": "HC Energie Karlovy Vary (junioři) – Wikipedie",
        "href": "https://cs.wikipedia.org/wiki/HC_Energie_Karlovy_Vary_(junio%C5%99i)",
        "real_result": true
      },
      {
        "title": "HC Energie Karlovy Vary, s.r.o. (Karlovy Vary) • Firmy.cz",
        "href": "https://www.firmy.cz/detail/13176853-hc-energie-karlovy-vary-karlovy-vary.html",
        "real_result": true
      },
      {
        "title": "Potvrzeno. Karlovy Vary povedou šampioni z Nagana",
        "href": "https://www.sport.cz/clanek/hokej-extraliga-potvrzeno-karlovy-vary-maji-nove-trenery-5025312",
        "real_result": true
      },
      {
        "title": "HC Energie Karlovy Vary spol. s. r.o. | Karlovy Vary",
        "href": "https://www.karlovyvary.cz/cs/hc-energie-karlovy-vary-spol-s-ro",
        "real_result": true
      },
      {
        "title": "HC Energie Karlovy VARY s.r.o., Karlovy Vary - Živéfirmy.cz",
        "href": "https://www.zivefirmy.cz/hc-energie-karlovy-vary_f1125276",
        "real_result": true
      },
      {
        "title": "Trenérská rošáda na západě Čech. Energii opustil Bruk, tým povede Eismann",
        "href": "https://karlovarsky.denik.cz/hokej_region/trenerska-rosada-na-zapade-cech-energii-opustil-bruk-tym-povede-eismann-20240206.html",
        "real_result": true
      }
    ],
    "user": "anon_ratio_low",
    "timestamp": "2024-04-03T11:38:00.607Z"
  },
  {
    "query": "levné ubytování",
    "language": "queries",
    "results": [
      {
        "title": "Česká republika - Rezervujte a ušetřete až 50%",
        "href": "http://www.booking.com/country/cz.cs.html",
        "real_result": true
      },
      {
        "title": "Hotel.cz - ubytování v ČR - Nechte se u nás inspirovat",
        "href": "https://www.hotel.cz/",
        "real_result": true
      },
      {
        "title": "Slevomat: Nabídky ubytování - 200 nových nabídek denně",
        "href": "https://www.slevomat.cz/cestovani",
        "real_result": true
      },
      {
        "title": "Levné ubytování - výhodné ceny - Brno 19 min. každých 15 min.",
        "href": "http://www.podhorkou.cz/hotel.htm",
        "real_result": true
      },
      {
        "title": "Levné ubytování v Praze | LevnéUbytování.net",
        "href": "https://www.levneubytovani.net/cechy/praha/",
        "real_result": true
      },
      {
        "title": "Penziony.cz – Levné ubytování, hotely, apartmány, pensiony…",
        "href": "https://www.penziony.cz/",
        "real_result": true
      },
      {
        "title": "Ubytování Beskydy - levné chaty a chalupy k pronajmutí…",
        "href": "https://www.e-chalupy.cz/ubytovani_beskydy_dovolena.php",
        "real_result": true
      },
      {
        "title": "Obrázky›Levné ubytování",
        "href": "/obrazky/?q=levn%C3%A9+ubytov%C3%A1n%C3%AD&fulltext=&sourceid=fulltext&thru=hint-obrazky-carousel#utm_content=carousel&utm_term=levn%C3%A9%20ubytov%C3%A1n%C3%AD&utm_medium=hint&utm_source=search.seznam.cz",
        "real_result": false
      },
      {
        "title": "Nejlepších 10 levných hotelů v Praze, Česko | Booking.com",
        "href": "https://www.booking.com/budget/city/cz/prague.cs.html",
        "real_result": true
      },
      {
        "title": "Levné ubytování, Praha | Hotely Penziony .cz",
        "href": "https://www.hotelypenziony.cz/levneubytovani-praha-hornipocernice/",
        "real_result": true
      },
      {
        "title": "Služby›Levné ubytování",
        "href": "https://www.firmy.cz/sluzby/?q=levn%c3%a9%20ubytov%c3%a1n%c3%ad&geo=0&x=16.577500&y=49.167300&a=0.000000&utm_content=search-results&utm_term=levn%c3%a9%20ubytov%c3%a1n%c3%ad&utm_medium=hint&utm_source=search.seznam.cz",
        "real_result": false
      },
      {
        "title": "Pobyty i levné ubytování | Slevomat.cz",
        "href": "https://www.slevomat.cz/cestovani/pobyty-a-ubytovani",
        "real_result": true
      },
      {
        "title": "Levné apartmány",
        "href": "https://www.megaubytko.cz/apartmany/levne",
        "real_result": true
      },
      {
        "title": "Levné ubytování • Firmy.cz",
        "href": "https://www.firmy.cz/Cestovni-sluzby/Ubytovaci-sluzby/Levne-ubytovani",
        "real_result": true
      },
      {
        "title": "Levné ubytování - Vyhledávač ubytování - Rezervace - eSky",
        "href": "https://www.esky.cz/ubytovani/",
        "real_result": true
      },
      {
        "title": "Ubytování Praha | Hotely.cz",
        "href": "https://www.hotely.cz/praha",
        "real_result": true
      },
      {
        "title": "Nejlevnější ubytování v ČR - Nejnižší cena zaručena",
        "href": "https://www.megaubytko.cz/levne",
        "real_result": true
      },
      {
        "title": "Nejlepší ubytování na Skrz.cz - Největší výběr jedině na Skrz",
        "href": "https://skrz.cz/pobyty",
        "real_result": true
      },
      {
        "title": "4* hotel ve Znojmě - Sprcha s tropickým deštěm",
        "href": "https://www.premiumhotel.cz/cz/",
        "real_result": true
      }
    ],
    "user": "anon_ratio_low",
    "timestamp": "2024-04-03T11:54:33.437Z"
  },
  {
    "query": "HC Dynamo Pardubice",
    "language": "queries",
    "results": [
      {
        "title": "HC Dynamo Pardubice",
        "href": "/obrazky/?q=HC+Dynamo+Pardubice#utm_content=teamLeft&utm_term=HC Dynamo Pardubice&utm_medium=hint&utm_source=search.seznam.cz",
        "real_result": false
      },
      {
        "title": "HC Dynamo Pardubice – oficiální internetové stránky",
        "href": "https://www.hcdynamo.cz/",
        "real_result": true
      },
      {
        "title": "Hokejisté Litvínova budou usilovat o první semifinálovou výhru nad Pardubicemi",
        "href": "https://www.ceskenoviny.cz/zpravy/2500523",
        "real_result": true
      },
      {
        "title": "HC Dynamo Pardubice (Pardubice, Zelené Předměstí) • Firmy.cz",
        "href": "https://www.firmy.cz/detail/580010-hc-dynamo-pardubice-pardubice-zelene-predmesti.html",
        "real_result": true
      },
      {
        "title": "HC Dynamo Pardubice – Wikipedie",
        "href": "https://cs.wikipedia.org/wiki/HC_Dynamo_Pardubice",
        "real_result": true
      },
      {
        "title": "Hokejisté Pardubic zvládli i druhé semifinále, Litvínov porazili 3:0",
        "href": "https://www.ceskenoviny.cz/zpravy/2499660",
        "real_result": true
      },
      {
        "title": "Hockey CLUB Dynamo Pardubice a.s., Pardubice, Zelené Předměstí…",
        "href": "https://www.zivefirmy.cz/hockey-club-dynamo-pardubice_f274363",
        "real_result": true
      },
      {
        "title": "Obrázky›HC Dynamo Pardubice",
        "href": "/obrazky/?q=HC+Dynamo+Pardubice&fulltext=&sourceid=fulltext&thru=hint-obrazky-obrazky#utm_content=obrazky&utm_term=HC%20Dynamo%20Pardubice&utm_medium=hint&utm_source=search.seznam.cz",
        "real_result": false
      },
      {
        "title": "Hockey CLUB Dynamo Pardubice a.s. - IČO 60112476 - Obchodní…",
        "href": "https://www.podnikatel.cz/rejstrik/hockey-club-dynamo-pardubice-a-s-60112476/",
        "real_result": true
      },
      {
        "title": "HC Dynamo Pardubice a.s. - Česká poradna",
        "href": "https://www.ceskaporadna.cz/profil/hc-dynamo-pardubice-a-s",
        "real_result": true
      },
      {
        "title": "Hokej Pardubice - soupiska, posily, přestupy, stadion",
        "href": "https://www.hokejzpravy.cz/rubriky/extraliga/hokej-pardubice-soupiska-posily-prestupy-stadion_1236.html",
        "real_result": true
      },
      {
        "title": "Mountfield HK - HC Dynamo Pardubice | Hradec Králové.cz",
        "href": "https://kultura.hradeckralove.cz/mountfield-hk-hc-dynamo-pardubice-48857/",
        "real_result": true
      }
    ],
    "user": "anon_ratio_low",
    "timestamp": "2024-04-03T12:11:19.905Z"
  },
  {
    "query": "Norsko",
    "language": "queries",
    "results": [
      {
        "title": "Obrázky›Norsko",
        "href": "/obrazky/?q=Norsko&fulltext=&sourceid=fulltext&thru=hint-obrazky-super#utm_content=super&utm_term=Norsko&utm_medium=hint&utm_source=search.seznam.cz",
        "real_result": false
      },
      {
        "title": "Norge.cz - Norge.cz - Norsko a norština",
        "href": "https://norge.cz/",
        "real_result": true
      },
      {
        "title": "Norské království (1814) – Wikipedie",
        "href": "https://cs.wikipedia.org/wiki/Norsk%C3%A9_kr%C3%A1lovstv%C3%AD_(1814)",
        "real_result": true
      },
      {
        "title": "Sdovolená.cz›Tipy na   dovolenou  ",
        "href": "https://sdovolena.seznam.cz/search?country=147#source:hint-advert&utm_content=sdovolena&utm_term=Norsko&utm_medium=hint&utm_source=search.seznam.cz",
        "real_result": false
      },
      {
        "title": "Norsko - Česko 1:2, rozpačitý výkon, i tak výhra. Haškovu premiéru ozdobil Barák",
        "href": "https://www.idnes.cz/fotbal/euro-2024/norsko-cesko-fotbal-pripravne-utkani-v-oslu-premiera-trenera-ivana-haska.A240322_163131_euro-2024_min",
        "real_result": true
      },
      {
        "title": "Norsko – Wikipedie",
        "href": "https://cs.wikipedia.org/wiki/Norsko#:~:text=Norsko%20(norsky%20(bokm%C3%A5l)%20zvuk%20Norge%2C,Mayen%20a%20souostrov%C3%AD%20%C5%A0picberky%2C%5Bpozn.%202%5D",
        "real_result": true
      },
      {
        "title": "Norsko - Česko 1:2. Hašek začal výhrou, krásně rozhodl Barák",
        "href": "https://isport.blesk.cz/clanek/fotbal-reprezentace/445093/norsko-cesko-1-2-hasek-zacal-vyhrou-krasne-rozhodl-barak.html",
        "real_result": true
      },
      {
        "title": "Norsko - Wikiwand",
        "href": "https://www.wikiwand.com/cs/Norsko",
        "real_result": true
      },
      {
        "title": "Norsko",
        "href": "https://www.aktualne.cz/wiki/zahranici/norsko/r~886c305a7b0f11e5b3730025900fea04/",
        "real_result": true
      },
      {
        "title": "Videa›Norsko",
        "href": "//search.seznam.cz/videa/?q=Norsko#utm_content=organic&utm_term=Norsko&utm_medium=hint&utm_source=search.seznam.cz",
        "real_result": false
      },
      {
        "title": "Norsko není jen Haaland. Miláček Turků, syn herečky i rodinná tradice",
        "href": "https://isport.blesk.cz/clanek/fotbal-reprezentace/445063/norsko-neni-jen-haaland-milacek-turku-syn-herecky-i-rodinna-tradice.html?kapitola=2",
        "real_result": true
      },
      {
        "title": "Norsko – Multimediaexpo.cz",
        "href": "http://www.multimediaexpo.cz/mmecz/index.php/Norsko",
        "real_result": true
      },
      {
        "title": "Norské království, země Vikingů a králů. Jaká je historie?",
        "href": "https://www.ceskykralovskyinstitut.cz/norske-kralovstvi-1-cast-zeme-vikingu-a-kralu-jaka-je-jeho-historie/",
        "real_result": true
      }
    ],
    "user": "anon_ratio_low",
    "timestamp": "2024-04-03T12:27:52.390Z"
  },
  {
    "query": "cloudová úložiště",
    "language": "queries",
    "results": [
      {
        "title": "Cloudové úložiště již od 50 GB - 100% bezpečnost, vše v ČR",
        "href": "https://www.cestadocloudu.cz/owncloud/",
        "real_result": true
      },
      {
        "title": "Videa›Cloudová úložiště",
        "href": "//search.seznam.cz/videa/?q=cloudov%C3%A1+%C3%BAlo%C5%BEi%C5%A1t%C4%9B#utm_content=organic&utm_term=cloudov%C3%A1%20%C3%BAlo%C5%BEi%C5%A1t%C4%9B&utm_medium=hint&utm_source=search.seznam.cz",
        "real_result": false
      },
      {
        "title": "Cloudové úložiště – Wikipedie",
        "href": "https://cs.wikipedia.org/wiki/Cloudov%C3%A9_%C3%BAlo%C5%BEi%C5%A1t%C4%9B",
        "real_result": true
      },
      {
        "title": "TOP 5: Nejlepší cloudová úložiště 2023 - Markomu.cz",
        "href": "https://www.markomu.cz/nejlepsi-cloudova-uloziste/",
        "real_result": true
      },
      {
        "title": "Cloud Disk - velkokapacitní cloud úložiště pro vaše data",
        "href": "https://www.zonercloud.cz/produkty/cloud-disk",
        "real_result": true
      },
      {
        "title": "Co je cloudové úložiště? - 2024",
        "href": "https://zivotdivny.com/co-je-cloudove-uloziste/",
        "real_result": true
      },
      {
        "title": "Co je to cloudové úložiště? - ZCOM",
        "href": "https://www.zcom.cz/slovnicek-pojmu/co-je-to-cloudove-uloziste/",
        "real_result": true
      },
      {
        "title": "Cloudové úložiště 2024 → Srovnání Dropbox, OneDrive, iCloud a…",
        "href": "https://www.skrblik.cz/telefon/internet/cloudova-uloziste/",
        "real_result": true
      },
      {
        "title": "dTest: Jak vybrat cloudové úložiště - Nezávislé testy, víc než…",
        "href": "https://www.dtest.cz/clanek-6032/jak-vybrat-cloudove-uloziste",
        "real_result": true
      },
      {
        "title": "Co je cloudové úložiště a jak ho využít | Microsoft Azure",
        "href": "https://azure.microsoft.com/cs-cz/resources/cloud-computing-dictionary/what-is-cloud-storage",
        "real_result": true
      },
      {
        "title": "Cloudová úložiště | Kinet – Váš IT partner",
        "href": "https://www.kinet.cz/nase-sluzby/cloudova-uloziste/",
        "real_result": true
      },
      {
        "title": "Cloudová úložiště | epravo.cz",
        "href": "https://www.epravo.cz/top/clanky/cloudova-uloziste-105755.html",
        "real_result": true
      }
    ],
    "user": "anon_ratio_low",
    "timestamp": "2024-04-03T12:44:26.497Z"
  },
  {
    "query": "Oslo",
    "language": "queries",
    "results": [
      {
        "title": "Obrázky›Oslo",
        "href": "/obrazky/?q=Oslo&fulltext=&sourceid=fulltext&thru=hint-obrazky-super#utm_content=super&utm_term=Oslo&utm_medium=hint&utm_source=search.seznam.cz",
        "real_result": false
      },
      {
        "title": "Oslo - Česká Wikipedie",
        "href": "https://www.czech.wiki/wiki/Oslo",
        "real_result": true
      },
      {
        "title": "Oslo - Hlavní město | Turistika.cz",
        "href": "https://www.turistika.cz/mista/oslo/detail",
        "real_result": true
      },
      {
        "title": "Sdovolená.cz›Tipy na   dovolenou  ",
        "href": "https://sdovolena.seznam.cz/search?hotel=oslo#source:hint-advert&utm_content=sdovolena&utm_term=Oslo&utm_medium=hint&utm_source=search.seznam.cz",
        "real_result": false
      },
      {
        "title": "Oslo – Travel guide at Wikivoyage",
        "href": "https://en.wikivoyage.org/wiki/Oslo",
        "real_result": true
      },
      {
        "title": "Oslo",
        "href": "https://www.aktualne.cz/wiki/geografie/staty-a-mesta/oslo/r~8a216e46796811e48ee3002590604f2e/",
        "real_result": true
      },
      {
        "title": "Oslo | CK Palma Travel",
        "href": "https://www.palma-travel.cz/zeme/norsko/oslo/",
        "real_result": true
      },
      {
        "title": "Oslo: skleněná skandinávská metropole | Magazín Radynacestu.cz",
        "href": "https://www.radynacestu.cz/magazin/oslo/",
        "real_result": true
      },
      {
        "title": "Oslo - hlavní město Norska | Norsko | SLAN tour",
        "href": "https://slantour.cz/zajezdy/informace/oslo---hlavni-mesto-norska",
        "real_result": true
      },
      {
        "title": "Oslo: Město Nobelových cen, zábavných muzeí a dostupného…",
        "href": "https://www.jenprocestovatele.cz/oslo-mesto-nobelovych-cen-zabavnych-muzei-a-dostupneho-lyzovani/",
        "real_result": true
      },
      {
        "title": "Oslo aneb louka bohů: Město v romantickém fjordu a uprostřed zeleně",
        "href": "https://www.novinky.cz/clanek/cestovani-oslo-aneb-louka-bohu-mesto-v-romantickem-fjordu-a-uprostred-zelene-40404634",
        "real_result": true
      },
      {
        "title": "Oslov – Wikipedie",
        "href": "https://cs.wikipedia.org/wiki/Oslov",
        "real_result": true
      }
    ],
    "user": "anon_ratio_low",
    "timestamp": "2024-04-03T13:00:59.834Z"
  },
  {
    "query": "co jsou to big data",
    "language": "queries",
    "results": [
      {
        "title": "Big Data: Jaká je jejich využitelnost a co to znamená pro vás…",
        "href": "https://www.mesec.cz/clanky/big-data-jaka-je-jejich-vyuzitelnost-a-co-to-znamena-pro-vas/#:~:text=Obecn%C4%9B%20lze%20%C5%99%C3%ADci%2C%20%C5%BEe%20Big,videa%2C%20obr%C3%A1zky%2C%20dokumenty%20a%20dal%C5%A1%C3%AD.",
        "real_result": true
      },
      {
        "title": "Co je Big data? | Peach-dev",
        "href": "https://peach-dev.cz/wiki/big-data/",
        "real_result": true
      },
      {
        "title": "Big Data – proč je jejich zpracování budoucnost i možná cesta…",
        "href": "https://thinkeasy.cz/big-data-proc-je-jejich-zpracovani-budoucnost-i-mozna-cesta-do-pekel/",
        "real_result": true
      },
      {
        "title": "Big data: Co to je, jak se zpracovávají a kdo všechno je…",
        "href": "https://www.master.cz/blog/big-data-vysvetleni-a-zpracovani/",
        "real_result": true
      },
      {
        "title": "Big Data - ManagementMania.com",
        "href": "https://managementmania.com/cs/big-data",
        "real_result": true
      },
      {
        "title": "Co jsou big data a jak je můžete využít | Algotech",
        "href": "https://www.algotech.cz/novinky/big-data-co-to-je-a-jak-je-vyuzijete-ke-zvyseni-zisku",
        "real_result": true
      },
      {
        "title": "Co jsou big data? | Oracle Česká Republika",
        "href": "https://www.oracle.com/cz/big-data/what-is-big-data/",
        "real_result": true
      },
      {
        "title": "Big data",
        "href": "https://www.systemonline.cz/business-intelligence/big-data.htm",
        "real_result": true
      },
      {
        "title": "Co jsou BIG DATA a co nám mohou přinést | BusinessInfo.cz",
        "href": "https://www.businessinfo.cz/clanky/co-jsou-big-data-a-co-nam-mohou-prinest/",
        "real_result": true
      },
      {
        "title": "Velká data (big data): definice, výhody a výzvy (infografika…",
        "href": "https://www.europarl.europa.eu/topics/cs/article/20210211STO97614/velka-data-big-data-definice-vyhody-a-vyzvy-infografika",
        "real_result": true
      },
      {
        "title": "Big data - Nyní za akční cenu 334 Kč",
        "href": "https://www.megaknihy.cz/vysoka-skola/3019298-big-data-veda-o-datech-zaklady-a-aplikace.html",
        "real_result": true
      }
    ],
    "user": "anon_ratio_low",
    "timestamp": "2024-04-03T13:17:35.809Z"
  },
  {
    "query": "google flights",
    "language": "queries",
    "results": [
      {
        "title": "Google Flights - Find Cheap Flight Options & Track Prices",
        "href": "https://www.google.com/travel/flights",
        "real_result": true
      },
      {
        "title": "Google Flights - Wikipedia",
        "href": "https://en.wikipedia.org/wiki/Google_Flights",
        "real_result": true
      },
      {
        "title": "Letenky Google – levné letenky a sledování cen",
        "href": "https://www.google.com/travel/flights?hl=cs",
        "real_result": true
      },
      {
        "title": "Google Flights: co to je a jak používat online letovou…",
        "href": "https://movilforum.com/cs/google-lety%2C-co-to-je-a-jak-pou%C5%BE%C3%ADvat-online-letovou-platformu/",
        "real_result": true
      },
      {
        "title": "Google Flights: A How-to Guide to Finding Flight Deals in 2024",
        "href": "https://thriftytraveler.com/guides/google-flights/",
        "real_result": true
      },
      {
        "title": "Google",
        "href": "https://www.google.cz/travel/",
        "real_result": true
      },
      {
        "title": "Google Flights Explore Map - How to Use it to Find Cheap…",
        "href": "https://thevacationer.com/google-flights-explore/",
        "real_result": true
      },
      {
        "title": "Vyhledání letenek ve službě Letenky Google - Počítač - Nápověda…",
        "href": "https://support.google.com/travel/answer/2475306?hl=cs&co=GENIE.Platform%3DDesktop",
        "real_result": true
      },
      {
        "title": "How to Use Google Flights: A Guide to Finding Cheap Flights…",
        "href": "https://www.going.com/guides/how-to-use-google-flights",
        "real_result": true
      },
      {
        "title": "Google Flights: Best Tool For Booking Airline Tickets - One…",
        "href": "https://onemileatatime.com/guides/google-flights/",
        "real_result": true
      }
    ],
    "user": "anon_ratio_low",
    "timestamp": "2024-04-03T13:34:09.110Z"
  },
  {
    "query": "cloud porovnání",
    "language": "queries",
    "results": [
      {
        "title": "Jaké je nejlepší cloudové úložiště? Velké srovnání cloudových služeb pro rok 2022",
        "href": "https://www.cnews.cz/clanky/cloudove-uloziste-2022/",
        "real_result": true
      },
      {
        "title": "Nejlepší cloudové úložiště - srovnání v roce 2024",
        "href": "https://www.5nej.cz/srovnani-cloudovych-ulozist/",
        "real_result": true
      },
      {
        "title": "Internet věcí vs Cloud Computing: Rozdíl a srovnání",
        "href": "https://askanydifference.com/cs/difference-between-internet-of-things-and-cloud-computing-with-table/",
        "real_result": true
      },
      {
        "title": "Jaký vybrat cloud? Jaké je nejlepší cloudové úložiště…",
        "href": "https://www.youtube.com/watch?v=TYCNd-c2YOE",
        "real_result": true
      },
      {
        "title": "Srovnání cloudů - Je lepší Azure nebo AWS? - Srovnání cloudů…",
        "href": "https://www.linksoft.eu/cs/srovnani-cloudu-je-lepsi-azure-nebo-aws",
        "real_result": true
      },
      {
        "title": "Srovnání Cloudových Úložišť (uživatelské klady a zápory různých…",
        "href": "https://androidmarket.cz/ruzne/srovnani-cloudovych-ulozist-uzivatelske-klady-a-zapory-ruznych-sluzeb/",
        "real_result": true
      },
      {
        "title": "Velké srovnání cloudových úložišť: které je nejlepší?",
        "href": "https://mobilenet.cz/clanky/velke-srovnani-cloudovych-ulozist-ktere-je-nejlepsi-30300",
        "real_result": true
      },
      {
        "title": "Vyhledávejte a porovnávejte produkty | Produktvdetailu.cz",
        "href": "https://www.produktvdetailu.cz/",
        "real_result": true
      },
      {
        "title": "Bez cloudových služeb to dnes nejde. Která je pro vaši firmu nejlepší?",
        "href": "https://www.root.cz/pr-clanky/bez-cloudovych-sluzeb-to-dnes-nejde-ktera-je-pro-vasi-firmu-nejlepsi/",
        "real_result": true
      },
      {
        "title": "Přehled cloudových úložišť: které se aktuálně vyplatí?",
        "href": "https://www.zive.cz/clanky/prehled-cloudovych-ulozist-ktere-se-aktualne-vyplati/sc-3-a-180727/default.aspx",
        "real_result": true
      }
    ],
    "user": "anon_ratio_low",
    "timestamp": "2024-04-03T13:50:41.527Z"
  },
  {
    "query": "booking.com",
    "language": "queries",
    "results": [
      {
        "title": "Booking.com - Přes 1 200 000 ubytování",
        "href": "http://www.booking.com/index.html",
        "real_result": true
      },
      {
        "title": "Booking",
        "href": "http://www.booking.com/",
        "real_result": true
      },
      {
        "title": "Booking.com | Official site | The best hotels, flights, car…",
        "href": "https://www.booking.com/",
        "real_result": true
      },
      {
        "title": "Booking.com (Czech Republic) s.r.o. (Praha, Nové Město) • Firmy…",
        "href": "https://www.firmy.cz/detail/13282384-booking-com-czech-republic-s-r-o-praha-nove-mesto.html",
        "real_result": true
      },
      {
        "title": "Booking.com – Wikipedie",
        "href": "https://cs.wikipedia.org/wiki/Booking.com",
        "real_result": true
      },
      {
        "title": "Airbnb",
        "href": "https://cs.airbnb.com/",
        "real_result": true
      },
      {
        "title": "Booking.com - Wikipedia",
        "href": "https://en.wikipedia.org/wiki/Booking.com",
        "real_result": true
      },
      {
        "title": "10 nejlepších hotelů v Praze (od 962 Kč)",
        "href": "https://www.booking.com/city/cz/prague.cs.html",
        "real_result": true
      },
      {
        "title": "Booking.com - dasbestelexikon.de",
        "href": "https://www.dasbestelexikon.de/cs/wiki/Booking.com",
        "real_result": true
      },
      {
        "title": "Booking.com (Czech Republic) s.r.o. , Praha IČO 24816841…",
        "href": "https://rejstrik-firem.kurzy.cz/24816841/booking-com-czech-republic-sro/",
        "real_result": true
      },
      {
        "title": "Hledáte ubytování? Představujeme Booking.com! | Tipli",
        "href": "https://www.tipli.cz/clanek/hledate-ubytovani-predstavujeme-booking-com",
        "real_result": true
      }
    ],
    "user": "anon_ratio_low",
    "timestamp": "2024-04-03T14:07:11.797Z"
  },
  {
    "query": "extraliga tabulka",
    "language": "queries",
    "results": [
      {
        "title": "Extraliga ledního hokeje",
        "href": "/obrazky/?q=Extraliga+ledn%C3%ADho+hokeje#utm_content=leagueLeft&utm_term=extraliga tabulka&utm_medium=hint&utm_source=search.seznam.cz",
        "real_result": false
      },
      {
        "title": "Slovenská extraliga ledního hokeje 2023/2024 – Wikipedie",
        "href": "https://cs.wikipedia.org/wiki/Slovensk%C3%A1_extraliga_ledn%C3%ADho_hokeje_2023/2024",
        "real_result": true
      },
      {
        "title": "Tipsport extraliga statistiky - bodování, produktivita, střelci",
        "href": "https://www.betarena.cz/rubriky/hokej/extraliga-statistiky-bodovani-produktivita-strelci_7549.html",
        "real_result": true
      },
      {
        "title": "Tipsport Extraliga 2023/2024 tabulka - Hokej/Česko",
        "href": "https://www.livesport.cz/tipsport-extraliga/tabulka/",
        "real_result": true
      },
      {
        "title": "Extraliga hokej 2023/2024: informace, program, výsledky",
        "href": "https://www.betarena.cz/rubriky/sportovni-clanky/extraliga-ledniho-hokeje-informace-a-program_1517.html",
        "real_result": true
      },
      {
        "title": "Extraliga 2020/21: informace, program, výsledky, tabulka",
        "href": "https://www.sazeni-online.eu/blog/extraliga-2020-21-informace-program-vysledky-tabulka",
        "real_result": true
      },
      {
        "title": "HC Oceláři Třinec v české hokejové extralize 2023/2024…",
        "href": "https://cs.wikipedia.org/wiki/HC_Ocel%C3%A1%C5%99i_T%C5%99inec_v_%C4%8Desk%C3%A9_hokejov%C3%A9_extralize_2023/2024",
        "real_result": true
      },
      {
        "title": "Tabulka Extraligy v hokeji 2023/24: Tipsport ELH",
        "href": "https://www.sport.cz/sekce/hokej-extraliga-tabulky-25",
        "real_result": true
      },
      {
        "title": "Tabulky Tipsport extraligy ledního hokeje 2023/2024",
        "href": "https://www.irozhlas.cz/sport/elh/2023/tabulky",
        "real_result": true
      },
      {
        "title": "Extraliga muži 2023/2024 | Detail ligy | iSport.cz",
        "href": "https://isport.blesk.cz/vysledky/ostatni/liga?league=1090&season=5015",
        "real_result": true
      },
      {
        "title": "Tabulka: Chance LIGA | Hokej.cz - web českého hokeje",
        "href": "https://www.hokej.cz/chance-liga/table",
        "real_result": true
      }
    ],
    "user": "anon_ratio_low",
    "timestamp": "2024-04-03T14:23:44.616Z"
  },
  {
    "query": "jak velkou RAM do notebooku",
    "language": "queries",
    "results": [
      {
        "title": "Ram do notebooku - Alza dny jsou tady",
        "href": "https://www.alza.cz/pameti-ram-8-gb-pro-notebooky/18875391.htm",
        "real_result": true
      },
      {
        "title": "Kvalitní notebooky za top ceny - Když noťas, tak GIGACOMPUTER",
        "href": "https://www.gigacomputer.cz/predvadeci-notebooky/",
        "real_result": true
      },
      {
        "title": "Notebooky pro každého - Najdeš na CZC.cz",
        "href": "https://www.czc.cz/notebooky/produkty",
        "real_result": true
      },
      {
        "title": "Kolik paměti (RAM) potřebuji pro svůj notebook? | furbify",
        "href": "https://www.furbify.cz/blog/dobre-rady/kolik-pameti-ram-potrebuji-pro-svuj-notebook",
        "real_result": true
      },
      {
        "title": "jak si vybrat ram pro notebook | Gyoumagazine",
        "href": "https://cs.gyoumagazine.com/article/how_to_choose_ram_for_laptop",
        "real_result": true
      },
      {
        "title": "Velký průvodce operační pamětí RAM pro notebooky | HPmarket.cz",
        "href": "https://www.hpmarket.cz/document.asp?dc=kolik-ram-potrebujete",
        "real_result": true
      },
      {
        "title": "Jakou RAM si mám vybrat pro svůj notebook? – AutoTachki",
        "href": "https://cs.avtotachki.com/kakuyu-operativnuyu-pamyat-vybrat-dlya-moego-noutbuka/",
        "real_result": true
      },
      {
        "title": "Jak vybrat RAM? | Datart",
        "href": "https://www.datart.cz/novinky/radce/jak-vybrat-ram",
        "real_result": true
      },
      {
        "title": "Vybíráme notebook 3 – Operační paměť (RAM) | Lenovo Blog CZ",
        "href": "https://www.lenovoblog.cz/2018/06/vybirame-notebook-operacni-pamet-ram.html",
        "real_result": true
      },
      {
        "title": "Co je důležité u operačních pamětí (RAM) ? | Comfor.cz",
        "href": "https://www.comfor.cz/blog/co-je-dulezite-u-operacnich-pameti-(ram)",
        "real_result": true
      },
      {
        "title": "jakou RAM zvolit do notebooku - poradna Živě.cz",
        "href": "https://www.zive.cz/poradna/jakou-ram-zvolit-do-notebooku/sc-20-cq-600258/default.aspx?consultanswers=1",
        "real_result": true
      },
      {
        "title": "Kolik operační paměti RAM skutečně potřebuje váš počítač",
        "href": "https://www.idnes.cz/technet/pc-mac/ram-operacni-pamet-kolik-notebook-latence-rychlost.A211027_094417_hardware_dvr",
        "real_result": true
      },
      {
        "title": "Jak zjistit maximální velikost paměti RAM v notebooku",
        "href": "https://cs.soringpcrepair.com/how-to-find-out-max-supported-ram-on-laptop/",
        "real_result": true
      },
      {
        "title": "Notebooky - Objednejte ihned na DATART.cz",
        "href": "https://www.datart.cz/pc-notebooky.html",
        "real_result": true
      },
      {
        "title": "Nejlepší operační paměti 2024 - Aktuální srovnání celého trhu",
        "href": "https://www.testado.cz/operacni-pameti/",
        "real_result": true
      },
      {
        "title": "Notebooky - Nakupte na allegro.cz",
        "href": "https://allegro.cz/kategorie/pocitace-notebooky-491",
        "real_result": true
      }
    ],
    "user": "anon_ratio_low",
    "timestamp": "2024-04-03T14:40:22.853Z"
  },
  {
    "query": "mistrovství světa v hokeji 2024",
    "language": "queries",
    "results": [
      {
        "title": "Mistrovství světa v ledním hokeji 2024 (Divize II) – Wikipedie",
        "href": "https://cs.wikipedia.org/wiki/Mistrovstv%C3%AD_sv%C4%9Bta_v_ledn%C3%ADm_hokeji_2024_(Divize_II)",
        "real_result": true
      },
      {
        "title": "MS v para hokeji 2024: program, výsledky, tabulka, Češi",
        "href": "https://www.hokejzpravy.cz/rubriky/ms-v-hokeji/ms-v-para-hokeji-program-vysledky-tabulka-cesi_1537.html",
        "real_result": true
      },
      {
        "title": "Mistrovství světa v ledním hokeji 2024 – Wikipedie",
        "href": "https://cs.wikipedia.org/wiki/Mistrovstv%C3%AD_sv%C4%9Bta_v_ledn%C3%ADm_hokeji_2024",
        "real_result": true
      },
      {
        "title": "Mistrovství světa v ledním hokeji 2024 (Divize III) – Wikipedie",
        "href": "https://cs.wikipedia.org/wiki/Mistrovstv%C3%AD_sv%C4%9Bta_v_ledn%C3%ADm_hokeji_2024_(Divize_III)",
        "real_result": true
      },
      {
        "title": "Mistrovství světa v ledním hokeji 2024 – Kudy z nudy",
        "href": "https://www.kudyznudy.cz/akce/mistrovstvi-sveta-v-lednim-hokeji-2024",
        "real_result": true
      },
      {
        "title": "Mistrovství světa v ledním hokeji 2024: program",
        "href": "https://www.betarena.cz/rubriky/hokej/mistrovstvi-sveta-v-lednim-hokeji-program_1420.html",
        "real_result": true
      },
      {
        "title": "Vstupenky NA Mistrovství Světa IIHF V Ledním Hokeji 2024 | ms…",
        "href": "https://ms2024.ticketportal.cz/mslh2024",
        "real_result": true
      },
      {
        "title": "MS v hokeji 2024: program a skupiny šampionátu v ČR. Kdy hrají Češi?",
        "href": "https://isport.blesk.cz/ms-v-hokeji-2024-program-skupiny-vstupenky",
        "real_result": true
      },
      {
        "title": "MS v hokeji 2024 - Výsledky, program, reportáže online - Idnes…",
        "href": "https://www.idnes.cz/hokej/ms-2024",
        "real_result": true
      },
      {
        "title": "MS v hokeji 2024: Co všechno zatím víme o domácím hokejovém šampionátu?",
        "href": "https://cnn.iprima.cz/ms-v-hokeji-2024-87609",
        "real_result": true
      }
    ],
    "user": "anon_ratio_low",
    "timestamp": "2024-04-03T14:57:12.132Z"
  },
  {
    "query": "autonomní vozidla",
    "language": "queries",
    "results": [
      {
        "title": "Videa›Autonomní vozidla",
        "href": "//search.seznam.cz/videa/?q=autonomn%C3%AD+vozidla#utm_content=organic&utm_term=autonomn%C3%AD%20vozidla&utm_medium=hint&utm_source=search.seznam.cz",
        "real_result": false
      },
      {
        "title": "Autonomní vozidlo – Wikipedie",
        "href": "https://cs.wikipedia.org/wiki/Autonomn%C3%AD_vozidlo",
        "real_result": true
      },
      {
        "title": "TEST Autonomní Audi A7 Concept na vlastní kůži: Jízda bez…",
        "href": "https://www.auto.cz/test-autonomni-audi-a7-concept-na-vlastni-kuzi-jizda-bez-ridice-dokaze-byt-desiva-108794",
        "real_result": true
      },
      {
        "title": "Autonomní řízení – proč ho stále nemáme a kdy se dočkáme?",
        "href": "https://www.portalridice.cz/clanek/autonomni-rizeni-proc-ho-stale-nemame-a-kdy-se-dockame",
        "real_result": true
      },
      {
        "title": "Autonomní auta pomalu vznikají, je to hudba budoucnosti…",
        "href": "https://www.srovnator.cz/clanky/autonomni-automobily/",
        "real_result": true
      },
      {
        "title": "Autonomní jízda silničních vozidel - Časopis Elektro - Odborné…",
        "href": "http://www.odbornecasopisy.cz/elektro/clanek/autonomni-jizda-silnicnich-vozidel--3746",
        "real_result": true
      },
      {
        "title": "Autonomní řízení a robotické taxíky jsou stále větší fiasko. Odmítá je většina lidí a ještě víc těch, kteří zažili jízdu s nimi",
        "href": "https://www.autoforum.cz/predstaveni/z-autonomniho-rizeni-a-robotickych-taxiku-je-stale-vetsi-fiasko-odmita-je-vetsina-lidi-a-jeste-vice-tech-kteri-zazili-jizdu-s-nimi/",
        "real_result": true
      },
      {
        "title": "Autonomní řízení dopodrobna: Co si představit pod pěti stupni…",
        "href": "https://www.autoweb.cz/autonomni-rizeni-dopodrobna-si-predstavit-peti-stupni-automatizace/",
        "real_result": true
      },
      {
        "title": "Autonomní Tesly budou příští rok jezdit i v Evropě. Bez rukou na volantu to ale zatím nepůjde",
        "href": "https://www.zive.cz/clanky/autonomni-tesly-budou-pristi-rok-jezdit-i-v-evrope-bez-rukou-na-volantu-to-ale-zatim-nepujde/sc-3-a-227028/default.aspx",
        "real_result": true
      },
      {
        "title": "Pět stupňů k autonomnímu řízení - Škoda Storyboard",
        "href": "https://www.skoda-storyboard.com/cs/skoda-svet-cs/inovace-a-technologie/pet-stupnu-k-autonomnimu-rizeni/",
        "real_result": true
      },
      {
        "title": "Samoříditelná auta: Kde leží budoucnost autonomie vozidel…",
        "href": "https://www.allianz.cz/cs_CZ/pojisteni/vse-o-allianz/centrum-clanku/samoriditelna-auta-kde-lezi-budoucnost-autonomie-vozidel.html",
        "real_result": true
      }
    ],
    "user": "anon_ratio_low",
    "timestamp": "2024-04-03T15:13:49.387Z"
  },
  {
    "query": "jak funguje SSD",
    "language": "queries",
    "results": [
      {
        "title": "Jak funguje SSD disk: Přehledný průvodce pro začátečníky",
        "href": "https://vysvetleno.eu/vysvetlujeme/jak-funguje-ssd-disk/",
        "real_result": true
      },
      {
        "title": "Videa›Jak funguje SSD",
        "href": "//search.seznam.cz/videa/?q=jak+funguje+SSD#utm_content=organic&utm_term=jak%20funguje%20SSD&utm_medium=hint&utm_source=search.seznam.cz",
        "real_result": false
      },
      {
        "title": "Kouzlo SSD 1. díl: základní pojmy | Lenovo Blog CZ",
        "href": "https://www.lenovoblog.cz/2014/05/kouzlo-ssd-mini-serial.html",
        "real_result": true
      },
      {
        "title": "Co je SSD?",
        "href": "https://jencropable.com/cs/advices/31418-what-is-ssd",
        "real_result": true
      },
      {
        "title": "Co Dělá Ssd Disk?",
        "href": "https://soubory.info/app/4420/co-dela-ssd-disk",
        "real_result": true
      },
      {
        "title": "TIP#1265: Nákupní rádce: Co je to SSD. A proč je velmi důležité…",
        "href": "https://365tipu.cz/2019/01/04/tip1265-co-je-to-ssd-a-proc-je-velmi-dulezite-aby-vas-pocitac-prave-ssd-disk-mel/",
        "real_result": true
      },
      {
        "title": "Co je to SSD disk? | Počítače24.cz",
        "href": "https://www.pocitace24.cz/rubriky/blog/co-je-to-ssd-disk/",
        "real_result": true
      },
      {
        "title": "SSD - co se skrývá uvnitř - Technologie - Notebook.cz",
        "href": "https://notebook.cz/clanky/technologie/2009/ssd-disky",
        "real_result": true
      },
      {
        "title": "Co je jednotka SSD (Solid State Drive) a potřebuji ji?",
        "href": "https://apcaglobal.com/cs/9501-what-is-a-solid-state-drive-ssd-and-do-i-need-one.html",
        "real_result": true
      },
      {
        "title": "Co byste měli vědět o SSD discích | PHGame.cz",
        "href": "https://phgame.cz/7015/co-by-jste-meli-vedet-o-ssd-discich/",
        "real_result": true
      },
      {
        "title": "Jak TRIM funguje? - Technologie LC",
        "href": "https://lc-tech.com/cs/jak-trim-funguje/",
        "real_result": true
      }
    ],
    "user": "anon_ratio_low",
    "timestamp": "2024-04-03T15:30:29.303Z"
  }
]